<?xml version="1.0" encoding="UTF-8"?>
<list xmlns:xsi="http://www.w3.org/2001/XMLSchema-instance" xsi:noNamespaceSchemaLocation="../../xsd/spawns.xsd">
	<spawn name="CursedVillage">
		<group>
			<npc id="34641" x="60307" y="-44039" z="-3003" heading="48870" respawnTime="60sec" />
			<npc id="34642" x="61092" y="-43323" z="-2996" heading="43774" respawnTime="60sec" />
			<npc id="34643" x="59307" y="-43429" z="-2998" heading="52961" respawnTime="60sec" />
			<npc id="34644" x="60008" y="-44695" z="-2997" heading="5065" respawnTime="60sec" />
		</group>
	</spawn>
	<spawn name="Prison2">
		<group name="Prison_1" spawnByDefault="true">
			<territories>
				<territory shape="NPoly" minZ="-3200" maxZ="-2800">					
					<node x="59028" y="-42001" />
					<node x="58509" y="-42541" />
					<node x="58556" y="-43280" />
					<node x="59219" y="-43193" />
					<node x="59717" y="-42800" />
					<node x="59920" y="-42192" />
					<node x="59743" y="-41998" />
				</territory>
			</territories>
			<npc id="34638" count="20" respawnTime="60sec" />
			<npc id="34640" count="20" respawnTime="60sec" />
		</group>
	</spawn>
	<spawn name="Prison1">
		<group name="Prison_2" spawnByDefault="true">
			<territories>
				<territory shape="NPoly" minZ="-3200" maxZ="-2800">					
					<node x="58607" y="-45418" />
					<node x="59882" y="-45411" />
					<node x="59815" y="-44863" />
					<node x="59587" y="-44480" />
					<node x="59110" y="-44192" />
					<node x="58542" y="-44217" />
				</territory>
			</territories>
			<npc id="34637" count="20" respawnTime="60sec" />
			<npc id="34639" count="20" respawnTime="60sec" />
		</group>
	</spawn>
</list>
