<?xml version="1.0" encoding="UTF-8"?>
<list xmlns:xsi="http://www.w3.org/2001/XMLSchema-instance" xsi:noNamespaceSchemaLocation="../../xsd/spawns.xsd">
	<spawn name="DragonValleyWest"> <!-- MOB -->
		<territories>
			<territory name="dragon_valley" shape="Cylinder" minZ="-3800" maxZ="-3300" rad="200">
				<node x="79591" y="115522" />
			</territory>
		</territories>
		<npc id="24664" count="3" respawnTime="10sec" respawnRandom="0sec" chaseRange="1200" /> <!-- Graveyard Death Lich -->
		<npc id="24665" count="3" respawnTime="10sec" respawnRandom="0sec" chaseRange="1200" /> <!-- Graveyard Death Berserker -->
		<npc id="24666" count="3" respawnTime="10sec" respawnRandom="0sec" chaseRange="1200" /> <!-- Graveyard Death Soldier -->
		<npc id="24667" count="3" respawnTime="10sec" respawnRandom="0sec" chaseRange="1200" /> <!-- Graveyard Death Knight -->
	</spawn>
	<spawn>
		<territories>
			<territory name="dragon_valley" shape="Cylinder" minZ="-3100" maxZ="-2600" rad="200">
				<node x="83128" y="118378" />
			</territory>
		</territories>
		<npc id="24664" count="3" respawnTime="10sec" respawnRandom="0sec" chaseRange="1200" /> <!-- Graveyard Death Lich -->
		<npc id="24665" count="3" respawnTime="10sec" respawnRandom="0sec" chaseRange="1200" /> <!-- Graveyard Death Berserker -->
		<npc id="24666" count="3" respawnTime="10sec" respawnRandom="0sec" chaseRange="1200" /> <!-- Graveyard Death Soldier -->
		<npc id="24667" count="3" respawnTime="10sec" respawnRandom="0sec" chaseRange="1200" /> <!-- Graveyard Death Knight -->
	</spawn>
	<spawn>
		<territories>
			<territory name="dragon_valley" shape="Cylinder" minZ="-3100" maxZ="-2600" rad="200">
				<node x="84745" y="116521" />
			</territory>
		</territories>
		<npc id="24664" count="3" respawnTime="10sec" respawnRandom="0sec" chaseRange="1200" /> <!-- Graveyard Death Lich -->
		<npc id="24665" count="3" respawnTime="10sec" respawnRandom="0sec" chaseRange="1200" /> <!-- Graveyard Death Berserker -->
		<npc id="24666" count="3" respawnTime="10sec" respawnRandom="0sec" chaseRange="1200" /> <!-- Graveyard Death Soldier -->
		<npc id="24667" count="3" respawnTime="10sec" respawnRandom="0sec" chaseRange="1200" /> <!-- Graveyard Death Knight -->
	</spawn>
	<spawn>
		<territories>
			<territory name="dragon_valley" shape="Cylinder" minZ="-3000" maxZ="-2500" rad="200">
				<node x="84199" y="120463" />
			</territory>
		</territories>
		<npc id="24664" count="3" respawnTime="10sec" respawnRandom="0sec" chaseRange="1200" /> <!-- Graveyard Death Lich -->
		<npc id="24665" count="3" respawnTime="10sec" respawnRandom="0sec" chaseRange="1200" /> <!-- Graveyard Death Berserker -->
		<npc id="24666" count="3" respawnTime="10sec" respawnRandom="0sec" chaseRange="1200" /> <!-- Graveyard Death Soldier -->
		<npc id="24667" count="3" respawnTime="10sec" respawnRandom="0sec" chaseRange="1200" /> <!-- Graveyard Death Knight -->
	</spawn>
	<spawn>
		<territories>
			<territory name="dragon_valley" shape="Cylinder" minZ="-3100" maxZ="-2600" rad="200">
				<node x="86490" y="120737" />
			</territory>
		</territories>
		<npc id="24664" count="3" respawnTime="10sec" respawnRandom="0sec" chaseRange="1200" /> <!-- Graveyard Death Lich -->
		<npc id="24665" count="3" respawnTime="10sec" respawnRandom="0sec" chaseRange="1200" /> <!-- Graveyard Death Berserker -->
		<npc id="24666" count="3" respawnTime="10sec" respawnRandom="0sec" chaseRange="1200" /> <!-- Graveyard Death Soldier -->
		<npc id="24667" count="3" respawnTime="10sec" respawnRandom="0sec" chaseRange="1200" /> <!-- Graveyard Death Knight -->
	</spawn>
	<spawn>
		<territories>
			<territory name="dragon_valley" shape="Cylinder" minZ="-3100" maxZ="-2600" rad="200">
				<node x="88926" y="119497" />
			</territory>
		</territories>
		<npc id="24664" count="3" respawnTime="10sec" respawnRandom="0sec" chaseRange="1200" /> <!-- Graveyard Death Lich -->
		<npc id="24665" count="3" respawnTime="10sec" respawnRandom="0sec" chaseRange="1200" /> <!-- Graveyard Death Berserker -->
		<npc id="24666" count="3" respawnTime="10sec" respawnRandom="0sec" chaseRange="1200" /> <!-- Graveyard Death Soldier -->
		<npc id="24667" count="3" respawnTime="10sec" respawnRandom="0sec" chaseRange="1200" /> <!-- Graveyard Death Knight -->
	</spawn>
	<spawn>
		<territories>
			<territory name="dragon_valley" shape="Cylinder" minZ="-3100" maxZ="-2600" rad="200">
				<node x="90929" y="118266" />
			</territory>
		</territories>
		<npc id="24664" count="3" respawnTime="10sec" respawnRandom="0sec" chaseRange="1200" /> <!-- Graveyard Death Lich -->
		<npc id="24665" count="3" respawnTime="10sec" respawnRandom="0sec" chaseRange="1200" /> <!-- Graveyard Death Berserker -->
		<npc id="24666" count="3" respawnTime="10sec" respawnRandom="0sec" chaseRange="1200" /> <!-- Graveyard Death Soldier -->
		<npc id="24667" count="3" respawnTime="10sec" respawnRandom="0sec" chaseRange="1200" /> <!-- Graveyard Death Knight -->
	</spawn>
	<spawn>
		<territories>
			<territory name="dragon_valley" shape="Cylinder" minZ="-3000" maxZ="-2500" rad="200">
				<node x="91195" y="120308" />
			</territory>
		</territories>
		<npc id="24664" count="3" respawnTime="10sec" respawnRandom="0sec" chaseRange="1200" /> <!-- Graveyard Death Lich -->
		<npc id="24665" count="3" respawnTime="10sec" respawnRandom="0sec" chaseRange="1200" /> <!-- Graveyard Death Berserker -->
		<npc id="24666" count="3" respawnTime="10sec" respawnRandom="0sec" chaseRange="1200" /> <!-- Graveyard Death Soldier -->
		<npc id="24667" count="3" respawnTime="10sec" respawnRandom="0sec" chaseRange="1200" /> <!-- Graveyard Death Knight -->
	</spawn>
	<spawn>
		<territories>
			<territory name="dragon_valley" shape="Cylinder" minZ="-3100" maxZ="-2600" rad="200">
				<node x="92994" y="119077" />
			</territory>
		</territories>
		<npc id="24664" count="3" respawnTime="10sec" respawnRandom="0sec" chaseRange="1200" /> <!-- Graveyard Death Lich -->
		<npc id="24665" count="3" respawnTime="10sec" respawnRandom="0sec" chaseRange="1200" /> <!-- Graveyard Death Berserker -->
		<npc id="24666" count="3" respawnTime="10sec" respawnRandom="0sec" chaseRange="1200" /> <!-- Graveyard Death Soldier -->
		<npc id="24667" count="3" respawnTime="10sec" respawnRandom="0sec" chaseRange="1200" /> <!-- Graveyard Death Knight -->
	</spawn>
	<spawn>
		<territories>
			<territory name="dragon_valley" shape="Cylinder" minZ="-3100" maxZ="-2600" rad="200">
				<node x="94924" y="116198" />
			</territory>
		</territories>
		<npc id="24664" count="3" respawnTime="10sec" respawnRandom="0sec" chaseRange="1200" /> <!-- Graveyard Death Lich -->
		<npc id="24665" count="3" respawnTime="10sec" respawnRandom="0sec" chaseRange="1200" /> <!-- Graveyard Death Berserker -->
		<npc id="24666" count="3" respawnTime="10sec" respawnRandom="0sec" chaseRange="1200" /> <!-- Graveyard Death Soldier -->
		<npc id="24667" count="3" respawnTime="10sec" respawnRandom="0sec" chaseRange="1200" /> <!-- Graveyard Death Knight -->
	</spawn>
	<spawn>
		<territories>
			<territory name="dragon_valley" shape="Cylinder" minZ="-3200" maxZ="-2700" rad="200">
				<node x="92468" y="114995" />
			</territory>
		</territories>
		<npc id="24664" count="3" respawnTime="10sec" respawnRandom="0sec" chaseRange="1200" /> <!-- Graveyard Death Lich -->
		<npc id="24665" count="3" respawnTime="10sec" respawnRandom="0sec" chaseRange="1200" /> <!-- Graveyard Death Berserker -->
		<npc id="24666" count="3" respawnTime="10sec" respawnRandom="0sec" chaseRange="1200" /> <!-- Graveyard Death Soldier -->
		<npc id="24667" count="3" respawnTime="10sec" respawnRandom="0sec" chaseRange="1200" /> <!-- Graveyard Death Knight -->
	</spawn>
	<spawn>
		<territories>
			<territory name="dragon_valley" shape="Cylinder" minZ="-3100" maxZ="-2600" rad="200">
				<node x="90891" y="113329" />
			</territory>
		</territories>
		<npc id="24664" count="3" respawnTime="10sec" respawnRandom="0sec" chaseRange="1200" /> <!-- Graveyard Death Lich -->
		<npc id="24665" count="3" respawnTime="10sec" respawnRandom="0sec" chaseRange="1200" /> <!-- Graveyard Death Berserker -->
		<npc id="24666" count="3" respawnTime="10sec" respawnRandom="0sec" chaseRange="1200" /> <!-- Graveyard Death Soldier -->
		<npc id="24667" count="3" respawnTime="10sec" respawnRandom="0sec" chaseRange="1200" /> <!-- Graveyard Death Knight -->
	</spawn>
	<spawn>
		<territories>
			<territory name="dragon_valley" shape="Cylinder" minZ="-3100" maxZ="-2600" rad="200">
				<node x="92766" y="111938" />
			</territory>
		</territories>
		<npc id="24664" count="3" respawnTime="10sec" respawnRandom="0sec" chaseRange="1200" /> <!-- Graveyard Death Lich -->
		<npc id="24665" count="3" respawnTime="10sec" respawnRandom="0sec" chaseRange="1200" /> <!-- Graveyard Death Berserker -->
		<npc id="24666" count="3" respawnTime="10sec" respawnRandom="0sec" chaseRange="1200" /> <!-- Graveyard Death Soldier -->
		<npc id="24667" count="3" respawnTime="10sec" respawnRandom="0sec" chaseRange="1200" /> <!-- Graveyard Death Knight -->
	</spawn>
	<spawn>
		<territories>
			<territory name="dragon_valley" shape="Cylinder" minZ="-3300" maxZ="-2800" rad="200">
				<node x="88374" y="112291" />
			</territory>
		</territories>
		<npc id="24664" count="3" respawnTime="10sec" respawnRandom="0sec" chaseRange="1200" /> <!-- Graveyard Death Lich -->
		<npc id="24665" count="3" respawnTime="10sec" respawnRandom="0sec" chaseRange="1200" /> <!-- Graveyard Death Berserker -->
		<npc id="24666" count="3" respawnTime="10sec" respawnRandom="0sec" chaseRange="1200" /> <!-- Graveyard Death Soldier -->
		<npc id="24667" count="3" respawnTime="10sec" respawnRandom="0sec" chaseRange="1200" /> <!-- Graveyard Death Knight -->
	</spawn>
	<spawn>
		<territories>
			<territory name="dragon_valley" shape="Cylinder" minZ="-3100" maxZ="-2600" rad="200">
				<node x="85567" y="112128" />
			</territory>
		</territories>
		<npc id="24664" count="3" respawnTime="10sec" respawnRandom="0sec" chaseRange="1200" /> <!-- Graveyard Death Lich -->
		<npc id="24665" count="3" respawnTime="10sec" respawnRandom="0sec" chaseRange="1200" /> <!-- Graveyard Death Berserker -->
		<npc id="24666" count="3" respawnTime="10sec" respawnRandom="0sec" chaseRange="1200" /> <!-- Graveyard Death Soldier -->
		<npc id="24667" count="3" respawnTime="10sec" respawnRandom="0sec" chaseRange="1200" /> <!-- Graveyard Death Knight -->
	</spawn>
	<spawn>
		<territories>
			<territory name="dragon_valley" shape="Cylinder" minZ="-3100" maxZ="-2600" rad="200">
				<node x="83288" y="113027" />
			</territory>
		</territories>
		<npc id="24664" count="3" respawnTime="10sec" respawnRandom="0sec" chaseRange="1200" /> <!-- Graveyard Death Lich -->
		<npc id="24665" count="3" respawnTime="10sec" respawnRandom="0sec" chaseRange="1200" /> <!-- Graveyard Death Berserker -->
		<npc id="24666" count="3" respawnTime="10sec" respawnRandom="0sec" chaseRange="1200" /> <!-- Graveyard Death Soldier -->
		<npc id="24667" count="3" respawnTime="10sec" respawnRandom="0sec" chaseRange="1200" /> <!-- Graveyard Death Knight -->
	</spawn>
	<spawn>
		<territories>
			<territory name="dragon_valley" shape="Cylinder" minZ="-3100" maxZ="-2600" rad="200">
				<node x="90031" y="108254" />
			</territory>
		</territories>
		<npc id="24664" count="3" respawnTime="10sec" respawnRandom="0sec" chaseRange="1200" /> <!-- Graveyard Death Lich -->
		<npc id="24665" count="3" respawnTime="10sec" respawnRandom="0sec" chaseRange="1200" /> <!-- Graveyard Death Berserker -->
		<npc id="24666" count="3" respawnTime="10sec" respawnRandom="0sec" chaseRange="1200" /> <!-- Graveyard Death Soldier -->
		<npc id="24667" count="3" respawnTime="10sec" respawnRandom="0sec" chaseRange="1200" /> <!-- Graveyard Death Knight -->
	</spawn>
	<spawn>
		<territories>
			<territory name="dragon_valley" shape="Cylinder" minZ="-3300" maxZ="-2800" rad="200">
				<node x="89737" y="105801" />
			</territory>
		</territories>
		<npc id="24664" count="3" respawnTime="10sec" respawnRandom="0sec" chaseRange="1200" /> <!-- Graveyard Death Lich -->
		<npc id="24665" count="3" respawnTime="10sec" respawnRandom="0sec" chaseRange="1200" /> <!-- Graveyard Death Berserker -->
		<npc id="24666" count="3" respawnTime="10sec" respawnRandom="0sec" chaseRange="1200" /> <!-- Graveyard Death Soldier -->
		<npc id="24667" count="3" respawnTime="10sec" respawnRandom="0sec" chaseRange="1200" /> <!-- Graveyard Death Knight -->
	</spawn>
	<spawn>
		<territories>
			<territory name="dragon_valley" shape="Cylinder" minZ="-3200" maxZ="-2700" rad="200">
				<node x="87688" y="107141" />
			</territory>
		</territories>
		<npc id="24664" count="3" respawnTime="10sec" respawnRandom="0sec" chaseRange="1200" /> <!-- Graveyard Death Lich -->
		<npc id="24665" count="3" respawnTime="10sec" respawnRandom="0sec" chaseRange="1200" /> <!-- Graveyard Death Berserker -->
		<npc id="24666" count="3" respawnTime="10sec" respawnRandom="0sec" chaseRange="1200" /> <!-- Graveyard Death Soldier -->
		<npc id="24667" count="3" respawnTime="10sec" respawnRandom="0sec" chaseRange="1200" /> <!-- Graveyard Death Knight -->
	</spawn>
	<spawn>
		<territories>
			<territory name="dragon_valley" shape="Cylinder" minZ="-3300" maxZ="-2800" rad="200">
				<node x="85457" y="108284" />
			</territory>
		</territories>
		<npc id="24664" count="3" respawnTime="10sec" respawnRandom="0sec" chaseRange="1200" /> <!-- Graveyard Death Lich -->
		<npc id="24665" count="3" respawnTime="10sec" respawnRandom="0sec" chaseRange="1200" /> <!-- Graveyard Death Berserker -->
		<npc id="24666" count="3" respawnTime="10sec" respawnRandom="0sec" chaseRange="1200" /> <!-- Graveyard Death Soldier -->
		<npc id="24667" count="3" respawnTime="10sec" respawnRandom="0sec" chaseRange="1200" /> <!-- Graveyard Death Knight -->
	</spawn>
	<spawn>
		<territories>
			<territory name="dragon_valley" shape="Cylinder" minZ="-3100" maxZ="-2600" rad="200">
				<node x="81451" y="109348" />
			</territory>
		</territories>
		<npc id="24664" count="3" respawnTime="10sec" respawnRandom="0sec" chaseRange="1200" /> <!-- Graveyard Death Lich -->
		<npc id="24665" count="3" respawnTime="10sec" respawnRandom="0sec" chaseRange="1200" /> <!-- Graveyard Death Berserker -->
		<npc id="24666" count="3" respawnTime="10sec" respawnRandom="0sec" chaseRange="1200" /> <!-- Graveyard Death Soldier -->
		<npc id="24667" count="3" respawnTime="10sec" respawnRandom="0sec" chaseRange="1200" /> <!-- Graveyard Death Knight -->
	</spawn>
	<spawn>
		<territories>
			<territory name="dragon_valley" shape="Cylinder" minZ="-3700" maxZ="-3200" rad="200">
				<node x="81675" y="111776" />
			</territory>
		</territories>
		<npc id="24664" count="3" respawnTime="10sec" respawnRandom="0sec" chaseRange="1200" /> <!-- Graveyard Death Lich -->
		<npc id="24665" count="3" respawnTime="10sec" respawnRandom="0sec" chaseRange="1200" /> <!-- Graveyard Death Berserker -->
		<npc id="24666" count="3" respawnTime="10sec" respawnRandom="0sec" chaseRange="1200" /> <!-- Graveyard Death Soldier -->
		<npc id="24667" count="3" respawnTime="10sec" respawnRandom="0sec" chaseRange="1200" /> <!-- Graveyard Death Knight -->
	</spawn>
	<spawn>
		<territories>
			<territory name="dragon_valley" shape="Cylinder" minZ="-3700" maxZ="-3200" rad="200">
				<node x="111776" y="111776" />
			</territory>
		</territories>
		<npc id="24664" count="3" respawnTime="10sec" respawnRandom="0sec" chaseRange="1200" /> <!-- Graveyard Death Lich -->
		<npc id="24665" count="3" respawnTime="10sec" respawnRandom="0sec" chaseRange="1200" /> <!-- Graveyard Death Berserker -->
		<npc id="24666" count="3" respawnTime="10sec" respawnRandom="0sec" chaseRange="1200" /> <!-- Graveyard Death Soldier -->
		<npc id="24667" count="3" respawnTime="10sec" respawnRandom="0sec" chaseRange="1200" /> <!-- Graveyard Death Knight -->
	</spawn>
	<spawn>
		<territories>
			<territory name="dragon_valley" shape="Cylinder" minZ="-3800" maxZ="-3300" rad="200">
				<node x="83926" y="110580" />
			</territory>
		</territories>
		<npc id="24664" count="3" respawnTime="10sec" respawnRandom="0sec" chaseRange="1200" /> <!-- Graveyard Death Lich -->
		<npc id="24665" count="3" respawnTime="10sec" respawnRandom="0sec" chaseRange="1200" /> <!-- Graveyard Death Berserker -->
		<npc id="24666" count="3" respawnTime="10sec" respawnRandom="0sec" chaseRange="1200" /> <!-- Graveyard Death Soldier -->
		<npc id="24667" count="3" respawnTime="10sec" respawnRandom="0sec" chaseRange="1200" /> <!-- Graveyard Death Knight -->
	</spawn>
	<spawn>
		<territories>
			<territory name="dragon_valley" shape="Cylinder" minZ="-3800" maxZ="-3300" rad="200">
				<node x="86763" y="110259" />
			</territory>
		</territories>
		<npc id="24664" count="3" respawnTime="10sec" respawnRandom="0sec" chaseRange="1200" /> <!-- Graveyard Death Lich -->
		<npc id="24665" count="3" respawnTime="10sec" respawnRandom="0sec" chaseRange="1200" /> <!-- Graveyard Death Berserker -->
		<npc id="24666" count="3" respawnTime="10sec" respawnRandom="0sec" chaseRange="1200" /> <!-- Graveyard Death Soldier -->
		<npc id="24667" count="3" respawnTime="10sec" respawnRandom="0sec" chaseRange="1200" /> <!-- Graveyard Death Knight -->
	</spawn>
	<spawn>
		<territories>
			<territory name="dragon_valley" shape="Cylinder" minZ="-3700" maxZ="-3200" rad="200">
				<node x="90334" y="111208" />
			</territory>
		</territories>
		<npc id="24664" count="3" respawnTime="10sec" respawnRandom="0sec" chaseRange="1200" /> <!-- Graveyard Death Lich -->
		<npc id="24665" count="3" respawnTime="10sec" respawnRandom="0sec" chaseRange="1200" /> <!-- Graveyard Death Berserker -->
		<npc id="24666" count="3" respawnTime="10sec" respawnRandom="0sec" chaseRange="1200" /> <!-- Graveyard Death Soldier -->
		<npc id="24667" count="3" respawnTime="10sec" respawnRandom="0sec" chaseRange="1200" /> <!-- Graveyard Death Knight -->
	</spawn>
	<spawn>
		<territories>
			<territory name="dragon_valley" shape="Cylinder" minZ="-3900" maxZ="-3400" rad="200">
				<node x="91928" y="109497" />
			</territory>
		</territories>
		<npc id="24664" count="3" respawnTime="10sec" respawnRandom="0sec" chaseRange="1200" /> <!-- Graveyard Death Lich -->
		<npc id="24665" count="3" respawnTime="10sec" respawnRandom="0sec" chaseRange="1200" /> <!-- Graveyard Death Berserker -->
		<npc id="24666" count="3" respawnTime="10sec" respawnRandom="0sec" chaseRange="1200" /> <!-- Graveyard Death Soldier -->
		<npc id="24667" count="3" respawnTime="10sec" respawnRandom="0sec" chaseRange="1200" /> <!-- Graveyard Death Knight -->
	</spawn>
	<spawn>
		<territories>
			<territory name="dragon_valley" shape="Cylinder" minZ="-3800" maxZ="-3300" rad="200">
				<node x="94480" y="109835" />
			</territory>
		</territories>
		<npc id="24664" count="3" respawnTime="10sec" respawnRandom="0sec" chaseRange="1200" /> <!-- Graveyard Death Lich -->
		<npc id="24665" count="3" respawnTime="10sec" respawnRandom="0sec" chaseRange="1200" /> <!-- Graveyard Death Berserker -->
		<npc id="24666" count="3" respawnTime="10sec" respawnRandom="0sec" chaseRange="1200" /> <!-- Graveyard Death Soldier -->
		<npc id="24667" count="3" respawnTime="10sec" respawnRandom="0sec" chaseRange="1200" /> <!-- Graveyard Death Knight -->
	</spawn>
	<spawn>
		<territories>
			<territory name="dragon_valley" shape="Cylinder" minZ="-3800" maxZ="-3300" rad="200">
				<node x="97401" y="109542" />
			</territory>
		</territories>
		<npc id="24664" count="3" respawnTime="10sec" respawnRandom="0sec" chaseRange="1200" /> <!-- Graveyard Death Lich -->
		<npc id="24665" count="3" respawnTime="10sec" respawnRandom="0sec" chaseRange="1200" /> <!-- Graveyard Death Berserker -->
		<npc id="24666" count="3" respawnTime="10sec" respawnRandom="0sec" chaseRange="1200" /> <!-- Graveyard Death Soldier -->
		<npc id="24667" count="3" respawnTime="10sec" respawnRandom="0sec" chaseRange="1200" /> <!-- Graveyard Death Knight -->
	</spawn>
	<spawn>
		<territories>
			<territory name="dragon_valley" shape="Cylinder" minZ="-3100" maxZ="-2700" rad="100">
				<node x="85207" y="118680" />
			</territory>
		</territories>
		<npc id="24663" count="1" respawnTime="10sec" respawnRandom="0sec" chaseRange="1200" /> <!-- Graveyard Death Archer -->
	</spawn>
	<spawn>
		<territories>
			<territory name="dragon_valley" shape="Cylinder" minZ="-3100" maxZ="-2600" rad="100">
				<node x="88785" y="120992" />
			</territory>
		</territories>
		<npc id="24663" count="1" respawnTime="10sec" respawnRandom="0sec" chaseRange="1200" /> <!-- Graveyard Death Archer -->
	</spawn>
	<spawn>
		<territories>
			<territory name="dragon_valley" shape="Cylinder" minZ="-3100" maxZ="-2600" rad="100">
				<node x="90199" y="119457" />
			</territory>
		</territories>
		<npc id="24663" count="1" respawnTime="10sec" respawnRandom="0sec" chaseRange="1200" /> <!-- Graveyard Death Archer -->
	</spawn>
	<spawn>
		<territories>
			<territory name="dragon_valley" shape="Cylinder" minZ="-3000" maxZ="-2500" rad="100">
				<node x="91641" y="119216" />
			</territory>
		</territories>
		<npc id="24663" count="1" respawnTime="10sec" respawnRandom="0sec" chaseRange="1200" /> <!-- Graveyard Death Archer -->
	</spawn>
	<spawn>
		<territories>
			<territory name="dragon_valley" shape="Cylinder" minZ="-3100" maxZ="-2600" rad="100">
				<node x="94452" y="117888" />
			</territory>
		</territories>
		<npc id="24663" count="1" respawnTime="10sec" respawnRandom="0sec" chaseRange="1200" /> <!-- Graveyard Death Archer -->
	</spawn>
	<spawn>
		<territories>
			<territory name="dragon_valley" shape="Cylinder" minZ="-3200" maxZ="-2700" rad="100">
				<node x="93976" y="113995" />
			</territory>
		</territories>
		<npc id="24663" count="1" respawnTime="10sec" respawnRandom="0sec" chaseRange="1200" /> <!-- Graveyard Death Archer -->
	</spawn>
	<spawn>
		<territories>
			<territory name="dragon_valley" shape="Cylinder" minZ="-3100" maxZ="-2600" rad="100">
				<node x="92311" y="113236" />
			</territory>
		</territories>
		<npc id="24663" count="1" respawnTime="10sec" respawnRandom="0sec" chaseRange="1200" /> <!-- Graveyard Death Archer -->
	</spawn>
	<spawn>
		<territories>
			<territory name="dragon_valley" shape="Cylinder" minZ="-3100" maxZ="-2600" rad="100">
				<node x="91403" y="112019" />
			</territory>
		</territories>
		<npc id="24663" count="1" respawnTime="10sec" respawnRandom="0sec" chaseRange="1200" /> <!-- Graveyard Death Archer -->
	</spawn>
	<spawn>
		<territories>
			<territory name="dragon_valley" shape="Cylinder" minZ="-3200" maxZ="-2700" rad="100">
				<node x="89795" y="112053" />
			</territory>
		</territories>
		<npc id="24663" count="1" respawnTime="10sec" respawnRandom="0sec" chaseRange="1200" /> <!-- Graveyard Death Archer -->
	</spawn>
	<spawn>
		<territories>
			<territory name="dragon_valley" shape="Cylinder" minZ="-3400" maxZ="-2900" rad="100">
				<node x="87151" y="111434" />
			</territory>
		</territories>
		<npc id="24663" count="1" respawnTime="10sec" respawnRandom="0sec" chaseRange="1200" /> <!-- Graveyard Death Archer -->
	</spawn>
	<spawn>
		<territories>
			<territory name="dragon_valley" shape="Cylinder" minZ="-3100" maxZ="-2600" rad="100">
				<node x="84084" y="111691" />
			</territory>
		</territories>
		<npc id="24663" count="1" respawnTime="10sec" respawnRandom="0sec" chaseRange="1200" /> <!-- Graveyard Death Archer -->
	</spawn>
	<spawn>
		<territories>
			<territory name="dragon_valley" shape="Cylinder" minZ="-3200" maxZ="-2700" rad="100">
				<node x="89119" y="107093" />
			</territory>
		</territories>
		<npc id="24663" count="1" respawnTime="10sec" respawnRandom="0sec" chaseRange="1200" /> <!-- Graveyard Death Archer -->
	</spawn>
	<spawn>
		<territories>
			<territory name="dragon_valley" shape="Cylinder" minZ="-3100" maxZ="-2600" rad="100">
				<node x="87145" y="108624" />
			</territory>
		</territories>
		<npc id="24663" count="1" respawnTime="10sec" respawnRandom="0sec" chaseRange="1200" /> <!-- Graveyard Death Archer -->
	</spawn>
	<spawn>
		<territories>
			<territory name="dragon_valley" shape="Cylinder" minZ="-3300" maxZ="-2800" rad="100">
				<node x="84207" y="109743" />
			</territory>
		</territories>
		<npc id="24663" count="1" respawnTime="10sec" respawnRandom="0sec" chaseRange="1200" /> <!-- Graveyard Death Archer -->
	</spawn>
	<spawn>
		<territories>
			<territory name="dragon_valley" shape="Cylinder" minZ="-3800" maxZ="-3300" rad="100">
				<node x="82416" y="110606" />
			</territory>
		</territories>
		<npc id="24663" count="1" respawnTime="10sec" respawnRandom="0sec" chaseRange="1200" /> <!-- Graveyard Death Archer -->
	</spawn>
	<spawn>
		<territories>
			<territory name="dragon_valley" shape="Cylinder" minZ="-3700" maxZ="-3200" rad="100">
				<node x="100525" y="111772" />
			</territory>
		</territories>
		<npc id="24663" count="1" respawnTime="10sec" respawnRandom="0sec" chaseRange="1200" /> <!-- Graveyard Death Archer -->
	</spawn>
	<spawn>
		<territories>
			<territory name="dragon_valley" shape="Cylinder" minZ="-3700" maxZ="-3200" rad="100">
				<node x="101117" y="112511" />
			</territory>
		</territories>
		<npc id="24663" count="1" respawnTime="10sec" respawnRandom="0sec" chaseRange="1200" /> <!-- Graveyard Death Archer -->
	</spawn>
	<spawn>
		<territories>
			<territory name="dragon_valley" shape="Cylinder" minZ="-3800" maxZ="-3300" rad="200">
				<node x="99679" y="110404" />
			</territory>
		</territories>
		<npc id="24669" count="3" respawnTime="10sec" respawnRandom="0sec" chaseRange="1200" /> <!-- Dragon Officer -->
		<npc id="24670" count="3" respawnTime="10sec" respawnRandom="0sec" chaseRange="1200" /> <!-- Dragon Beast -->
		<npc id="24671" count="3" respawnTime="10sec" respawnRandom="0sec" chaseRange="1200" /> <!-- Dragon Centurion -->
		<npc id="24672" count="3" respawnTime="10sec" respawnRandom="0sec" chaseRange="1200" /> <!-- Elite Dragon Guard -->
	</spawn>
	<spawn>
		<territories>
			<territory name="dragon_valley" shape="Cylinder" minZ="-3800" maxZ="-3300" rad="200">
				<node x="102087" y="111301" />
			</territory>
		</territories>
		<npc id="24669" count="3" respawnTime="10sec" respawnRandom="0sec" chaseRange="1200" /> <!-- Dragon Officer -->
		<npc id="24670" count="3" respawnTime="10sec" respawnRandom="0sec" chaseRange="1200" /> <!-- Dragon Beast -->
		<npc id="24671" count="3" respawnTime="10sec" respawnRandom="0sec" chaseRange="1200" /> <!-- Dragon Centurion -->
		<npc id="24672" count="3" respawnTime="10sec" respawnRandom="0sec" chaseRange="1200" /> <!-- Elite Dragon Guard -->
	</spawn>
	<spawn>
		<territories>
			<territory name="dragon_valley" shape="Cylinder" minZ="-3800" maxZ="-3300" rad="200">
				<node x="101713" y="113857" />
			</territory>
		</territories>
		<npc id="24669" count="3" respawnTime="10sec" respawnRandom="0sec" chaseRange="1200" /> <!-- Dragon Officer -->
		<npc id="24670" count="3" respawnTime="10sec" respawnRandom="0sec" chaseRange="1200" /> <!-- Dragon Beast -->
		<npc id="24671" count="3" respawnTime="10sec" respawnRandom="0sec" chaseRange="1200" /> <!-- Dragon Centurion -->
		<npc id="24672" count="3" respawnTime="10sec" respawnRandom="0sec" chaseRange="1200" /> <!-- Elite Dragon Guard -->
	</spawn>
	<spawn>
		<territories>
			<territory name="dragon_valley" shape="Cylinder" minZ="-3800" maxZ="-3300" rad="200">
				<node x="101490" y="121819" />
			</territory>
		</territories>
		<npc id="24669" count="3" respawnTime="10sec" respawnRandom="0sec" chaseRange="1200" /> <!-- Dragon Officer -->
		<npc id="24670" count="3" respawnTime="10sec" respawnRandom="0sec" chaseRange="1200" /> <!-- Dragon Beast -->
		<npc id="24671" count="3" respawnTime="10sec" respawnRandom="0sec" chaseRange="1200" /> <!-- Dragon Centurion -->
		<npc id="24672" count="3" respawnTime="10sec" respawnRandom="0sec" chaseRange="1200" /> <!-- Elite Dragon Guard -->
	</spawn>
	<spawn>
		<territories>
			<territory name="dragon_valley" shape="Cylinder" minZ="-3800" maxZ="-3300" rad="200">
				<node x="102442" y="124140" />
			</territory>
		</territories>
		<npc id="24669" count="3" respawnTime="10sec" respawnRandom="0sec" chaseRange="1200" /> <!-- Dragon Officer -->
		<npc id="24670" count="3" respawnTime="10sec" respawnRandom="0sec" chaseRange="1200" /> <!-- Dragon Beast -->
		<npc id="24671" count="3" respawnTime="10sec" respawnRandom="0sec" chaseRange="1200" /> <!-- Dragon Centurion -->
		<npc id="24672" count="3" respawnTime="10sec" respawnRandom="0sec" chaseRange="1200" /> <!-- Elite Dragon Guard -->
	</spawn>
	<spawn>
		<territories>
			<territory name="dragon_valley" shape="Cylinder" minZ="-3700" maxZ="-3200" rad="200">
				<node x="104278" y="120442" />
			</territory>
		</territories>
		<npc id="24669" count="3" respawnTime="10sec" respawnRandom="0sec" chaseRange="1200" /> <!-- Dragon Officer -->
		<npc id="24670" count="3" respawnTime="10sec" respawnRandom="0sec" chaseRange="1200" /> <!-- Dragon Beast -->
		<npc id="24671" count="3" respawnTime="10sec" respawnRandom="0sec" chaseRange="1200" /> <!-- Dragon Centurion -->
		<npc id="24672" count="3" respawnTime="10sec" respawnRandom="0sec" chaseRange="1200" /> <!-- Elite Dragon Guard -->
	</spawn>
	<spawn>
		<territories>
			<territory name="dragon_valley" shape="Cylinder" minZ="-3800" maxZ="-3300" rad="200">
				<node x="104455" y="122634" />
			</territory>
		</territories>
		<npc id="24669" count="3" respawnTime="10sec" respawnRandom="0sec" chaseRange="1200" /> <!-- Dragon Officer -->
		<npc id="24670" count="3" respawnTime="10sec" respawnRandom="0sec" chaseRange="1200" /> <!-- Dragon Beast -->
		<npc id="24671" count="3" respawnTime="10sec" respawnRandom="0sec" chaseRange="1200" /> <!-- Dragon Centurion -->
		<npc id="24672" count="3" respawnTime="10sec" respawnRandom="0sec" chaseRange="1200" /> <!-- Elite Dragon Guard -->
	</spawn>
	<spawn>
		<territories>
			<territory name="dragon_valley" shape="Cylinder" minZ="-3800" maxZ="-3300" rad="200">
				<node x="106753" y="122847" />
			</territory>
		</territories>
		<npc id="24669" count="3" respawnTime="10sec" respawnRandom="0sec" chaseRange="1200" /> <!-- Dragon Officer -->
		<npc id="24670" count="3" respawnTime="10sec" respawnRandom="0sec" chaseRange="1200" /> <!-- Dragon Beast -->
		<npc id="24671" count="3" respawnTime="10sec" respawnRandom="0sec" chaseRange="1200" /> <!-- Dragon Centurion -->
		<npc id="24672" count="3" respawnTime="10sec" respawnRandom="0sec" chaseRange="1200" /> <!-- Elite Dragon Guard -->
	</spawn>
	<spawn>
		<territories>
			<territory name="dragon_valley" shape="Cylinder" minZ="-3800" maxZ="-3300" rad="200">
				<node x="106776" y="120510" />
			</territory>
		</territories>
		<npc id="24669" count="3" respawnTime="10sec" respawnRandom="0sec" chaseRange="1200" /> <!-- Dragon Officer -->
		<npc id="24670" count="3" respawnTime="10sec" respawnRandom="0sec" chaseRange="1200" /> <!-- Dragon Beast -->
		<npc id="24671" count="3" respawnTime="10sec" respawnRandom="0sec" chaseRange="1200" /> <!-- Dragon Centurion -->
		<npc id="24672" count="3" respawnTime="10sec" respawnRandom="0sec" chaseRange="1200" /> <!-- Elite Dragon Guard -->
	</spawn>
	<spawn>
		<territories>
			<territory name="dragon_valley" shape="Cylinder" minZ="-3800" maxZ="-3300" rad="200">
				<node x="109034" y="121369" />
			</territory>
		</territories>
		<npc id="24669" count="3" respawnTime="10sec" respawnRandom="0sec" chaseRange="1200" /> <!-- Dragon Officer -->
		<npc id="24670" count="3" respawnTime="10sec" respawnRandom="0sec" chaseRange="1200" /> <!-- Dragon Beast -->
		<npc id="24671" count="3" respawnTime="10sec" respawnRandom="0sec" chaseRange="1200" /> <!-- Dragon Centurion -->
		<npc id="24672" count="3" respawnTime="10sec" respawnRandom="0sec" chaseRange="1200" /> <!-- Elite Dragon Guard -->
	</spawn>
	<spawn>
		<territories>
			<territory name="dragon_valley" shape="Cylinder" minZ="-3700" maxZ="-3200" rad="200">
				<node x="109927" y="123372" />
			</territory>
		</territories>
		<npc id="24669" count="3" respawnTime="10sec" respawnRandom="0sec" chaseRange="1200" /> <!-- Dragon Officer -->
		<npc id="24670" count="3" respawnTime="10sec" respawnRandom="0sec" chaseRange="1200" /> <!-- Dragon Beast -->
		<npc id="24671" count="3" respawnTime="10sec" respawnRandom="0sec" chaseRange="1200" /> <!-- Dragon Centurion -->
		<npc id="24672" count="3" respawnTime="10sec" respawnRandom="0sec" chaseRange="1200" /> <!-- Elite Dragon Guard -->
	</spawn>
	<spawn>
		<territories>
			<territory name="dragon_valley" shape="Cylinder" minZ="-3800" maxZ="-3300" rad="200">
				<node x="110230" y="125797" />
			</territory>
		</territories>
		<npc id="24669" count="3" respawnTime="10sec" respawnRandom="0sec" chaseRange="1200" /> <!-- Dragon Officer -->
		<npc id="24670" count="3" respawnTime="10sec" respawnRandom="0sec" chaseRange="1200" /> <!-- Dragon Beast -->
		<npc id="24671" count="3" respawnTime="10sec" respawnRandom="0sec" chaseRange="1200" /> <!-- Dragon Centurion -->
		<npc id="24672" count="3" respawnTime="10sec" respawnRandom="0sec" chaseRange="1200" /> <!-- Elite Dragon Guard -->
	</spawn>
	<spawn>
		<territories>
			<territory name="dragon_valley" shape="Cylinder" minZ="-3800" maxZ="-3300" rad="200">
				<node x="112006" y="122479" />
			</territory>
		</territories>
		<npc id="24669" count="3" respawnTime="10sec" respawnRandom="0sec" chaseRange="1200" /> <!-- Dragon Officer -->
		<npc id="24670" count="3" respawnTime="10sec" respawnRandom="0sec" chaseRange="1200" /> <!-- Dragon Beast -->
		<npc id="24671" count="3" respawnTime="10sec" respawnRandom="0sec" chaseRange="1200" /> <!-- Dragon Centurion -->
		<npc id="24672" count="3" respawnTime="10sec" respawnRandom="0sec" chaseRange="1200" /> <!-- Elite Dragon Guard -->
	</spawn>
	<spawn>
		<territories>
			<territory name="dragon_valley" shape="Cylinder" minZ="-3900" maxZ="-3400" rad="200">
				<node x="113799" y="120547" />
			</territory>
		</territories>
		<npc id="24669" count="3" respawnTime="10sec" respawnRandom="0sec" chaseRange="1200" /> <!-- Dragon Officer -->
		<npc id="24670" count="3" respawnTime="10sec" respawnRandom="0sec" chaseRange="1200" /> <!-- Dragon Beast -->
		<npc id="24671" count="3" respawnTime="10sec" respawnRandom="0sec" chaseRange="1200" /> <!-- Dragon Centurion -->
		<npc id="24672" count="3" respawnTime="10sec" respawnRandom="0sec" chaseRange="1200" /> <!-- Elite Dragon Guard -->
	</spawn>
	<spawn>
		<territories>
			<territory name="dragon_valley" shape="Cylinder" minZ="-3700" maxZ="-3200" rad="200">
				<node x="116256" y="120400" />
			</territory>
		</territories>
		<npc id="24669" count="3" respawnTime="10sec" respawnRandom="0sec" chaseRange="1200" /> <!-- Dragon Officer -->
		<npc id="24670" count="3" respawnTime="10sec" respawnRandom="0sec" chaseRange="1200" /> <!-- Dragon Beast -->
		<npc id="24671" count="3" respawnTime="10sec" respawnRandom="0sec" chaseRange="1200" /> <!-- Dragon Centurion -->
		<npc id="24672" count="3" respawnTime="10sec" respawnRandom="0sec" chaseRange="1200" /> <!-- Elite Dragon Guard -->
	</spawn>
	<spawn>
		<territories>
			<territory name="dragon_valley" shape="Cylinder" minZ="-3700" maxZ="-3200" rad="200">
				<node x="117975" y="118773" />
			</territory>
		</territories>
		<npc id="24669" count="3" respawnTime="10sec" respawnRandom="0sec" chaseRange="1200" /> <!-- Dragon Officer -->
		<npc id="24670" count="3" respawnTime="10sec" respawnRandom="0sec" chaseRange="1200" /> <!-- Dragon Beast -->
		<npc id="24671" count="3" respawnTime="10sec" respawnRandom="0sec" chaseRange="1200" /> <!-- Dragon Centurion -->
		<npc id="24672" count="3" respawnTime="10sec" respawnRandom="0sec" chaseRange="1200" /> <!-- Elite Dragon Guard -->
	</spawn>
	<spawn>
		<territories>
			<territory name="dragon_valley" shape="Cylinder" minZ="-3800" maxZ="-3300" rad="200">
				<node x="116198" y="117226" />
			</territory>
		</territories>
		<npc id="24669" count="3" respawnTime="10sec" respawnRandom="0sec" chaseRange="1200" /> <!-- Dragon Officer -->
		<npc id="24670" count="3" respawnTime="10sec" respawnRandom="0sec" chaseRange="1200" /> <!-- Dragon Beast -->
		<npc id="24671" count="3" respawnTime="10sec" respawnRandom="0sec" chaseRange="1200" /> <!-- Dragon Centurion -->
		<npc id="24672" count="3" respawnTime="10sec" respawnRandom="0sec" chaseRange="1200" /> <!-- Elite Dragon Guard -->
	</spawn>
	<spawn>
		<territories>
			<territory name="dragon_valley" shape="Cylinder" minZ="-3700" maxZ="-3200" rad="200">
				<node x="120672" y="116831" />
			</territory>
		</territories>
		<npc id="24669" count="3" respawnTime="10sec" respawnRandom="0sec" chaseRange="1200" /> <!-- Dragon Officer -->
		<npc id="24670" count="3" respawnTime="10sec" respawnRandom="0sec" chaseRange="1200" /> <!-- Dragon Beast -->
		<npc id="24671" count="3" respawnTime="10sec" respawnRandom="0sec" chaseRange="1200" /> <!-- Dragon Centurion -->
		<npc id="24672" count="3" respawnTime="10sec" respawnRandom="0sec" chaseRange="1200" /> <!-- Elite Dragon Guard -->
	</spawn>
	<spawn>
		<territories>
			<territory name="dragon_valley" shape="Cylinder" minZ="-3700" maxZ="-3200" rad="200">
				<node x="122809" y="115622" />
			</territory>
		</territories>
		<npc id="24669" count="3" respawnTime="10sec" respawnRandom="0sec" chaseRange="1200" /> <!-- Dragon Officer -->
		<npc id="24670" count="3" respawnTime="10sec" respawnRandom="0sec" chaseRange="1200" /> <!-- Dragon Beast -->
		<npc id="24671" count="3" respawnTime="10sec" respawnRandom="0sec" chaseRange="1200" /> <!-- Dragon Centurion -->
		<npc id="24672" count="3" respawnTime="10sec" respawnRandom="0sec" chaseRange="1200" /> <!-- Elite Dragon Guard -->
	</spawn>
	<spawn>
		<territories>
			<territory name="dragon_valley" shape="Cylinder" minZ="-3800" maxZ="-3300" rad="200">
				<node x="120004" y="114601" />
			</territory>
		</territories>
		<npc id="24669" count="3" respawnTime="10sec" respawnRandom="0sec" chaseRange="1200" /> <!-- Dragon Officer -->
		<npc id="24670" count="3" respawnTime="10sec" respawnRandom="0sec" chaseRange="1200" /> <!-- Dragon Beast -->
		<npc id="24671" count="3" respawnTime="10sec" respawnRandom="0sec" chaseRange="1200" /> <!-- Dragon Centurion -->
		<npc id="24672" count="3" respawnTime="10sec" respawnRandom="0sec" chaseRange="1200" /> <!-- Elite Dragon Guard -->
	</spawn>
	<spawn>
		<territories>
			<territory name="dragon_valley" shape="Cylinder" minZ="-3900" maxZ="-3400" rad="200">
				<node x="121983" y="113102" />
			</territory>
		</territories>
		<npc id="24669" count="3" respawnTime="10sec" respawnRandom="0sec" chaseRange="1200" /> <!-- Dragon Officer -->
		<npc id="24670" count="3" respawnTime="10sec" respawnRandom="0sec" chaseRange="1200" /> <!-- Dragon Beast -->
		<npc id="24671" count="3" respawnTime="10sec" respawnRandom="0sec" chaseRange="1200" /> <!-- Dragon Centurion -->
		<npc id="24672" count="3" respawnTime="10sec" respawnRandom="0sec" chaseRange="1200" /> <!-- Elite Dragon Guard -->
	</spawn>
	<spawn>
		<territories>
			<territory name="dragon_valley" shape="Cylinder" minZ="-3800" maxZ="-3300" rad="200">
				<node x="122643" y="111026" />
			</territory>
		</territories>
		<npc id="24669" count="3" respawnTime="10sec" respawnRandom="0sec" chaseRange="1200" /> <!-- Dragon Officer -->
		<npc id="24670" count="3" respawnTime="10sec" respawnRandom="0sec" chaseRange="1200" /> <!-- Dragon Beast -->
		<npc id="24671" count="3" respawnTime="10sec" respawnRandom="0sec" chaseRange="1200" /> <!-- Dragon Centurion -->
		<npc id="24672" count="3" respawnTime="10sec" respawnRandom="0sec" chaseRange="1200" /> <!-- Elite Dragon Guard -->
	</spawn>
	<spawn>
		<territories>
			<territory name="dragon_valley" shape="Cylinder" minZ="-3100" maxZ="-2600" rad="200">
				<node x="120912" y="119934" />
			</territory>
		</territories>
		<npc id="24669" count="3" respawnTime="10sec" respawnRandom="0sec" chaseRange="1200" /> <!-- Dragon Officer -->
		<npc id="24670" count="3" respawnTime="10sec" respawnRandom="0sec" chaseRange="1200" /> <!-- Dragon Beast -->
		<npc id="24671" count="3" respawnTime="10sec" respawnRandom="0sec" chaseRange="1200" /> <!-- Dragon Centurion -->
		<npc id="24672" count="3" respawnTime="10sec" respawnRandom="0sec" chaseRange="1200" /> <!-- Elite Dragon Guard -->
	</spawn>
	<spawn>
		<territories>
			<territory name="dragon_valley" shape="Cylinder" minZ="-3100" maxZ="-2600" rad="200">
				<node x="119820" y="122114" />
			</territory>
		</territories>
		<npc id="24669" count="3" respawnTime="10sec" respawnRandom="0sec" chaseRange="1200" /> <!-- Dragon Officer -->
		<npc id="24670" count="3" respawnTime="10sec" respawnRandom="0sec" chaseRange="1200" /> <!-- Dragon Beast -->
		<npc id="24671" count="3" respawnTime="10sec" respawnRandom="0sec" chaseRange="1200" /> <!-- Dragon Centurion -->
		<npc id="24672" count="3" respawnTime="10sec" respawnRandom="0sec" chaseRange="1200" /> <!-- Elite Dragon Guard -->
	</spawn>
	<spawn>
		<territories>
			<territory name="dragon_valley" shape="Cylinder" minZ="-3200" maxZ="-2700" rad="200">
				<node x="117238" y="123075" />
			</territory>
		</territories>
		<npc id="24669" count="3" respawnTime="10sec" respawnRandom="0sec" chaseRange="1200" /> <!-- Dragon Officer -->
		<npc id="24670" count="3" respawnTime="10sec" respawnRandom="0sec" chaseRange="1200" /> <!-- Dragon Beast -->
		<npc id="24671" count="3" respawnTime="10sec" respawnRandom="0sec" chaseRange="1200" /> <!-- Dragon Centurion -->
		<npc id="24672" count="3" respawnTime="10sec" respawnRandom="0sec" chaseRange="1200" /> <!-- Elite Dragon Guard -->
	</spawn>
	<spawn>
		<territories>
			<territory name="dragon_valley" shape="Cylinder" minZ="-3100" maxZ="-2600" rad="200">
				<node x="109045" y="116384" />
			</territory>
		</territories>
		<npc id="24669" count="3" respawnTime="10sec" respawnRandom="0sec" chaseRange="1200" /> <!-- Dragon Officer -->
		<npc id="24670" count="3" respawnTime="10sec" respawnRandom="0sec" chaseRange="1200" /> <!-- Dragon Beast -->
		<npc id="24671" count="3" respawnTime="10sec" respawnRandom="0sec" chaseRange="1200" /> <!-- Dragon Centurion -->
		<npc id="24672" count="3" respawnTime="10sec" respawnRandom="0sec" chaseRange="1200" /> <!-- Elite Dragon Guard -->
	</spawn>
	<spawn>
		<territories>
			<territory name="dragon_valley" shape="Cylinder" minZ="-3100" maxZ="-2600" rad="200">
				<node x="109493" y="113662" />
			</territory>
		</territories>
		<npc id="24669" count="3" respawnTime="10sec" respawnRandom="0sec" chaseRange="1200" /> <!-- Dragon Officer -->
		<npc id="24670" count="3" respawnTime="10sec" respawnRandom="0sec" chaseRange="1200" /> <!-- Dragon Beast -->
		<npc id="24671" count="3" respawnTime="10sec" respawnRandom="0sec" chaseRange="1200" /> <!-- Dragon Centurion -->
		<npc id="24672" count="3" respawnTime="10sec" respawnRandom="0sec" chaseRange="1200" /> <!-- Elite Dragon Guard -->
	</spawn>
	<spawn>
		<territories>
			<territory name="dragon_valley" shape="Cylinder" minZ="-3100" maxZ="-2600" rad="200">
				<node x="108778" y="111418" />
			</territory>
		</territories>
		<npc id="24669" count="3" respawnTime="10sec" respawnRandom="0sec" chaseRange="1200" /> <!-- Dragon Officer -->
		<npc id="24670" count="3" respawnTime="10sec" respawnRandom="0sec" chaseRange="1200" /> <!-- Dragon Beast -->
		<npc id="24671" count="3" respawnTime="10sec" respawnRandom="0sec" chaseRange="1200" /> <!-- Dragon Centurion -->
		<npc id="24672" count="3" respawnTime="10sec" respawnRandom="0sec" chaseRange="1200" /> <!-- Elite Dragon Guard -->
	</spawn>
	<spawn>
		<territories>
			<territory name="dragon_valley" shape="Cylinder" minZ="-3000" maxZ="-2500" rad="200">
				<node x="112527" y="110084" />
			</territory>
		</territories>
		<npc id="24669" count="3" respawnTime="10sec" respawnRandom="0sec" chaseRange="1200" /> <!-- Dragon Officer -->
		<npc id="24670" count="3" respawnTime="10sec" respawnRandom="0sec" chaseRange="1200" /> <!-- Dragon Beast -->
		<npc id="24671" count="3" respawnTime="10sec" respawnRandom="0sec" chaseRange="1200" /> <!-- Dragon Centurion -->
		<npc id="24672" count="3" respawnTime="10sec" respawnRandom="0sec" chaseRange="1200" /> <!-- Elite Dragon Guard -->
	</spawn>
	<spawn>
		<territories>
			<territory name="dragon_valley" shape="Cylinder" minZ="-3200" maxZ="-2700" rad="200">
				<node x="114175" y="112200" />
			</territory>
		</territories>
		<npc id="24669" count="3" respawnTime="10sec" respawnRandom="0sec" chaseRange="1200" /> <!-- Dragon Officer -->
		<npc id="24670" count="3" respawnTime="10sec" respawnRandom="0sec" chaseRange="1200" /> <!-- Dragon Beast -->
		<npc id="24671" count="3" respawnTime="10sec" respawnRandom="0sec" chaseRange="1200" /> <!-- Dragon Centurion -->
		<npc id="24672" count="3" respawnTime="10sec" respawnRandom="0sec" chaseRange="1200" /> <!-- Elite Dragon Guard -->
	</spawn>
	<spawn>
		<territories>
			<territory name="dragon_valley" shape="Cylinder" minZ="-2800" maxZ="-2300" rad="200">
				<node x="111737" y="112385" />
			</territory>
		</territories>
		<npc id="24669" count="3" respawnTime="10sec" respawnRandom="0sec" chaseRange="1200" /> <!-- Dragon Officer -->
		<npc id="24670" count="3" respawnTime="10sec" respawnRandom="0sec" chaseRange="1200" /> <!-- Dragon Beast -->
		<npc id="24671" count="3" respawnTime="10sec" respawnRandom="0sec" chaseRange="1200" /> <!-- Dragon Centurion -->
		<npc id="24672" count="3" respawnTime="10sec" respawnRandom="0sec" chaseRange="1200" /> <!-- Elite Dragon Guard -->
	</spawn>
	<spawn>
		<territories>
			<territory name="dragon_valley" shape="Cylinder" minZ="-3100" maxZ="-2600" rad="200">
				<node x="115070" y="110033" />
			</territory>
		</territories>
		<npc id="24669" count="3" respawnTime="10sec" respawnRandom="0sec" chaseRange="1200" /> <!-- Dragon Officer -->
		<npc id="24670" count="3" respawnTime="10sec" respawnRandom="0sec" chaseRange="1200" /> <!-- Dragon Beast -->
		<npc id="24671" count="3" respawnTime="10sec" respawnRandom="0sec" chaseRange="1200" /> <!-- Dragon Centurion -->
		<npc id="24672" count="3" respawnTime="10sec" respawnRandom="0sec" chaseRange="1200" /> <!-- Elite Dragon Guard -->
	</spawn>
	<spawn>
		<territories>
			<territory name="dragon_valley" shape="Cylinder" minZ="-3000" maxZ="-2500" rad="200">
				<node x="118198" y="110121" />
			</territory>
		</territories>
		<npc id="24669" count="3" respawnTime="10sec" respawnRandom="0sec" chaseRange="1200" /> <!-- Dragon Officer -->
		<npc id="24670" count="3" respawnTime="10sec" respawnRandom="0sec" chaseRange="1200" /> <!-- Dragon Beast -->
		<npc id="24671" count="3" respawnTime="10sec" respawnRandom="0sec" chaseRange="1200" /> <!-- Dragon Centurion -->
		<npc id="24672" count="3" respawnTime="10sec" respawnRandom="0sec" chaseRange="1200" /> <!-- Elite Dragon Guard -->
	</spawn>
	<spawn>
		<territories>
			<territory name="dragon_valley" shape="Cylinder" minZ="-3100" maxZ="-2600" rad="200">
				<node x="120291" y="109726" />
			</territory>
		</territories>
		<npc id="24669" count="3" respawnTime="10sec" respawnRandom="0sec" chaseRange="1200" /> <!-- Dragon Officer -->
		<npc id="24670" count="3" respawnTime="10sec" respawnRandom="0sec" chaseRange="1200" /> <!-- Dragon Beast -->
		<npc id="24671" count="3" respawnTime="10sec" respawnRandom="0sec" chaseRange="1200" /> <!-- Dragon Centurion -->
		<npc id="24672" count="3" respawnTime="10sec" respawnRandom="0sec" chaseRange="1200" /> <!-- Elite Dragon Guard -->
	</spawn>
	<spawn>
		<territories>
			<territory name="dragon_valley" shape="Cylinder" minZ="-3100" maxZ="-2600" rad="200">
				<node x="122438" y="108496" />
			</territory>
		</territories>
		<npc id="24669" count="3" respawnTime="10sec" respawnRandom="0sec" chaseRange="1200" /> <!-- Dragon Officer -->
		<npc id="24670" count="3" respawnTime="10sec" respawnRandom="0sec" chaseRange="1200" /> <!-- Dragon Beast -->
		<npc id="24671" count="3" respawnTime="10sec" respawnRandom="0sec" chaseRange="1200" /> <!-- Dragon Centurion -->
		<npc id="24672" count="3" respawnTime="10sec" respawnRandom="0sec" chaseRange="1200" /> <!-- Elite Dragon Guard -->
	</spawn>
	<spawn>
		<territories>
			<territory name="dragon_valley" shape="Cylinder" minZ="-3100" maxZ="-2600" rad="200">
				<node x="124691" y="109473" />
			</territory>
		</territories>
		<npc id="24669" count="3" respawnTime="10sec" respawnRandom="0sec" chaseRange="1200" /> <!-- Dragon Officer -->
		<npc id="24670" count="3" respawnTime="10sec" respawnRandom="0sec" chaseRange="1200" /> <!-- Dragon Beast -->
		<npc id="24671" count="3" respawnTime="10sec" respawnRandom="0sec" chaseRange="1200" /> <!-- Dragon Centurion -->
		<npc id="24672" count="3" respawnTime="10sec" respawnRandom="0sec" chaseRange="1200" /> <!-- Elite Dragon Guard -->
	</spawn>
	<spawn>
		<territories>
			<territory name="dragon_valley" shape="Cylinder" minZ="-3200" maxZ="-2700" rad="200">
				<node x="125021" y="112061" />
			</territory>
		</territories>
		<npc id="24669" count="3" respawnTime="10sec" respawnRandom="0sec" chaseRange="1200" /> <!-- Dragon Officer -->
		<npc id="24670" count="3" respawnTime="10sec" respawnRandom="0sec" chaseRange="1200" /> <!-- Dragon Beast -->
		<npc id="24671" count="3" respawnTime="10sec" respawnRandom="0sec" chaseRange="1200" /> <!-- Dragon Centurion -->
		<npc id="24672" count="3" respawnTime="10sec" respawnRandom="0sec" chaseRange="1200" /> <!-- Elite Dragon Guard -->
	</spawn>
	<spawn>
		<territories>
			<territory name="dragon_valley" shape="Cylinder" minZ="-3200" maxZ="-2700" rad="200">
				<node x="116048" y="114673" />
			</territory>
		</territories>
		<npc id="24669" count="3" respawnTime="10sec" respawnRandom="0sec" chaseRange="1200" /> <!-- Dragon Officer -->
		<npc id="24670" count="3" respawnTime="10sec" respawnRandom="0sec" chaseRange="1200" /> <!-- Dragon Beast -->
		<npc id="24671" count="3" respawnTime="10sec" respawnRandom="0sec" chaseRange="1200" /> <!-- Dragon Centurion -->
		<npc id="24672" count="3" respawnTime="10sec" respawnRandom="0sec" chaseRange="1200" /> <!-- Elite Dragon Guard -->
	</spawn>
	<spawn>
		<territories>
			<territory name="dragon_valley" shape="Cylinder" minZ="-3300" maxZ="-2800" rad="200">
				<node x="113302" y="115434" />
			</territory>
		</territories>
		<npc id="24669" count="3" respawnTime="10sec" respawnRandom="0sec" chaseRange="1200" /> <!-- Dragon Officer -->
		<npc id="24670" count="3" respawnTime="10sec" respawnRandom="0sec" chaseRange="1200" /> <!-- Dragon Beast -->
		<npc id="24671" count="3" respawnTime="10sec" respawnRandom="0sec" chaseRange="1200" /> <!-- Dragon Centurion -->
		<npc id="24672" count="3" respawnTime="10sec" respawnRandom="0sec" chaseRange="1200" /> <!-- Elite Dragon Guard -->
	</spawn>
	<spawn>
		<territories>
			<territory name="dragon_valley" shape="Cylinder" minZ="-3100" maxZ="-2600" rad="200">
				<node x="112336" y="118189" />
			</territory>
		</territories>
		<npc id="24669" count="3" respawnTime="10sec" respawnRandom="0sec" chaseRange="1200" /> <!-- Dragon Officer -->
		<npc id="24670" count="3" respawnTime="10sec" respawnRandom="0sec" chaseRange="1200" /> <!-- Dragon Beast -->
		<npc id="24671" count="3" respawnTime="10sec" respawnRandom="0sec" chaseRange="1200" /> <!-- Dragon Centurion -->
		<npc id="24672" count="3" respawnTime="10sec" respawnRandom="0sec" chaseRange="1200" /> <!-- Elite Dragon Guard -->
	</spawn>
	<spawn>
		<territories>
			<territory name="dragon_valley" shape="Cylinder" minZ="-3700" maxZ="-3200" rad="100">
				<node x="102681" y="122761" />
			</territory>
		</territories>
		<npc id="24668" count="1" respawnTime="10sec" respawnRandom="0sec" chaseRange="1200" /> <!-- Dragon Peltast -->
	</spawn>
	<spawn>
		<territories>
			<territory name="dragon_valley" shape="Cylinder" minZ="-3800" maxZ="-3300" rad="100">
				<node x="103047" y="121630" />
			</territory>
		</territories>
		<npc id="24668" count="1" respawnTime="10sec" respawnRandom="0sec" chaseRange="1200" /> <!-- Dragon Peltast -->
	</spawn>
	<spawn>
		<territories>
			<territory name="dragon_valley" shape="Cylinder" minZ="-3800" maxZ="-3300" rad="100">
				<node x="105494" y="121572" />
			</territory>
		</territories>
		<npc id="24668" count="1" respawnTime="10sec" respawnRandom="0sec" chaseRange="1200" /> <!-- Dragon Peltast -->
	</spawn>
	<spawn>
		<territories>
			<territory name="dragon_valley" shape="Cylinder" minZ="-3700" maxZ="-3500" rad="100">
				<node x="105547" y="123739" />
			</territory>
		</territories>
		<npc id="24668" count="1" respawnTime="10sec" respawnRandom="0sec" chaseRange="1200" /> <!-- Dragon Peltast -->
	</spawn>
	<spawn>
		<territories>
			<territory name="dragon_valley" shape="Cylinder" minZ="-3800" maxZ="-3300" rad="100">
				<node x="107479" y="121593" />
			</territory>
		</territories>
		<npc id="24668" count="1" respawnTime="10sec" respawnRandom="0sec" chaseRange="1200" /> <!-- Dragon Peltast -->
	</spawn>
	<spawn>
		<territories>
			<territory name="dragon_valley" shape="Cylinder" minZ="-3700" maxZ="-3200" rad="100">
				<node x="108417" y="122629" />
			</territory>
		</territories>
		<npc id="24668" count="1" respawnTime="10sec" respawnRandom="0sec" chaseRange="1200" /> <!-- Dragon Peltast -->
	</spawn>
	<spawn>
		<territories>
			<territory name="dragon_valley" shape="Cylinder" minZ="-3700" maxZ="-3200" rad="100">
				<node x="110305" y="121958" />
			</territory>
		</territories>
		<npc id="24668" count="1" respawnTime="10sec" respawnRandom="0sec" chaseRange="1200" /> <!-- Dragon Peltast -->
	</spawn>
	<spawn>
		<territories>
			<territory name="dragon_valley" shape="Cylinder" minZ="-3800" maxZ="-3300" rad="100">
				<node x="111227" y="123929" />
			</territory>
		</territories>
		<npc id="24668" count="1" respawnTime="10sec" respawnRandom="0sec" chaseRange="1200" /> <!-- Dragon Peltast -->
	</spawn>
	<spawn>
		<territories>
			<territory name="dragon_valley" shape="Cylinder" minZ="-3800" maxZ="-3300" rad="100">
				<node x="115782" y="118912" />
			</territory>
		</territories>
		<npc id="24668" count="1" respawnTime="10sec" respawnRandom="0sec" chaseRange="1200" /> <!-- Dragon Peltast -->
	</spawn>
	<spawn>
		<territories>
			<territory name="dragon_valley" shape="Cylinder" minZ="-3800" maxZ="-3300" rad="100">
				<node x="116983" y="116168" />
			</territory>
		</territories>
		<npc id="24668" count="1" respawnTime="10sec" respawnRandom="0sec" chaseRange="1200" /> <!-- Dragon Peltast -->
	</spawn>
	<spawn>
		<territories>
			<territory name="dragon_valley" shape="Cylinder" minZ="-3700" maxZ="-3200" rad="100">
				<node x="121472" y="115177" />
			</territory>
		</territories>
		<npc id="24668" count="1" respawnTime="10sec" respawnRandom="0sec" chaseRange="1200" /> <!-- Dragon Peltast -->
	</spawn>
	<spawn>
		<territories>
			<territory name="dragon_valley" shape="Cylinder" minZ="-3100" maxZ="-2600" rad="100">
				<node x="121126" y="121373" />
			</territory>
		</territories>
		<npc id="24668" count="1" respawnTime="10sec" respawnRandom="0sec" chaseRange="1200" /> <!-- Dragon Peltast -->
	</spawn>
	<spawn>
		<territories>
			<territory name="dragon_valley" shape="Cylinder" minZ="-3100" maxZ="-2600" rad="100">
				<node x="108445" y="112541" />
			</territory>
		</territories>
		<npc id="24668" count="1" respawnTime="10sec" respawnRandom="0sec" chaseRange="1200" /> <!-- Dragon Peltast -->
	</spawn>
	<spawn>
		<territories>
			<territory name="dragon_valley" shape="Cylinder" minZ="-3100" maxZ="-2600" rad="100">
				<node x="110609" y="110555" />
			</territory>
		</territories>
		<npc id="24668" count="1" respawnTime="10sec" respawnRandom="0sec" chaseRange="1200" /> <!-- Dragon Peltast -->
	</spawn>
	<spawn>
		<territories>
			<territory name="dragon_valley" shape="Cylinder" minZ="-3100" maxZ="-2600" rad="100">
				<node x="113734" y="110673" />
			</territory>
		</territories>
		<npc id="24668" count="1" respawnTime="10sec" respawnRandom="0sec" chaseRange="1200" /> <!-- Dragon Peltast -->
	</spawn>
	<spawn>
		<territories>
			<territory name="dragon_valley" shape="Cylinder" minZ="-2800" maxZ="-2300" rad="100">
				<node x="112851" y="111494" />
			</territory>
		</territories>
		<npc id="24668" count="1" respawnTime="10sec" respawnRandom="0sec" chaseRange="1200" /> <!-- Dragon Peltast -->
	</spawn>
	<spawn>
		<territories>
			<territory name="dragon_valley" shape="Cylinder" minZ="-3100" maxZ="-2600" rad="100">
				<node x="119519" y="111014" />
			</territory>
		</territories>
		<npc id="24668" count="1" respawnTime="10sec" respawnRandom="0sec" chaseRange="1200" /> <!-- Dragon Peltast -->
	</spawn>
	<spawn>
		<territories>
			<territory name="dragon_valley" shape="Cylinder" minZ="-3000" maxZ="-2500" rad="100">
				<node x="120849" y="108163" />
			</territory>
		</territories>
		<npc id="24668" count="1" respawnTime="10sec" respawnRandom="0sec" chaseRange="1200" /> <!-- Dragon Peltast -->
	</spawn>
	<spawn>
		<territories>
			<territory name="dragon_valley" shape="Cylinder" minZ="-3100" maxZ="-2600" rad="100">
				<node x="123937" y="108349" />
			</territory>
		</territories>
		<npc id="24668" count="1" respawnTime="10sec" respawnRandom="0sec" chaseRange="1200" /> <!-- Dragon Peltast -->
	</spawn>
	<spawn>
		<territories>
			<territory name="dragon_valley" shape="Cylinder" minZ="-3200" maxZ="-2700" rad="100">
				<node x="125618" y="110804" />
			</territory>
		</territories>
		<npc id="24668" count="1" respawnTime="10sec" respawnRandom="0sec" chaseRange="1200" /> <!-- Dragon Peltast -->
	</spawn>
	<spawn>
		<territories>
			<territory name="dragon_valley" shape="Cylinder" minZ="-3200" maxZ="-2700" rad="100">
				<node x="114449" y="114757" />
			</territory>
		</territories>
		<npc id="24668" count="1" respawnTime="10sec" respawnRandom="0sec" chaseRange="1200" /> <!-- Dragon Peltast -->
	</spawn>
</list>
