<?xml version="1.0" encoding="UTF-8"?>
<list maintainEnchantment="true" xmlns:xsi="http://www.w3.org/2001/XMLSchema-instance" xsi:noNamespaceSchemaLocation="../xsd/multisell.xsd">
	<npcs>
		<npc>34212</npc> <!-- Black -->
	</npcs>
	<item>
		<ingredient id="17417" count="1" /> <!-- Helios Cutter -->
		<ingredient id="57" count="110596875" /> <!-- Adena -->
		<production id="17416" count="1" /> <!-- Helios Shaper -->
	</item>
	<item>
		<ingredient id="17418" count="1" /> <!-- Helios Slasher -->
		<ingredient id="57" count="110596875" /> <!-- Adena -->
		<production id="17416" count="1" /> <!-- Helios Shaper -->
	</item>
	<item>
		<ingredient id="17419" count="1" /> <!-- Helios Avenger -->
		<ingredient id="57" count="110596875" /> <!-- Adena -->
		<production id="17416" count="1" /> <!-- Helios Shaper -->
	</item>
	<item>
		<ingredient id="17420" count="1" /> <!-- Helios Fighter -->
		<ingredient id="57" count="110596875" /> <!-- Adena -->
		<production id="17416" count="1" /> <!-- Helios Shaper -->
	</item>
	<item>
		<ingredient id="17421" count="1" /> <!-- Helios Stormer -->
		<ingredient id="57" count="110596875" /> <!-- Adena -->
		<production id="17416" count="1" /> <!-- Helios Shaper -->
	</item>
	<item>
		<ingredient id="17422" count="1" /> <!-- Helios Thrower -->
		<ingredient id="57" count="110596875" /> <!-- Adena -->
		<production id="17416" count="1" /> <!-- Helios Shaper -->
	</item>
	<item>
		<ingredient id="17423" count="1" /> <!-- Helios Guardian -->
		<ingredient id="57" count="110596875" /> <!-- Adena -->
		<production id="17416" count="1" /> <!-- Helios Shaper -->
	</item>
	<item>
		<ingredient id="17424" count="1" /> <!-- Helios Buster -->
		<ingredient id="57" count="110596875" /> <!-- Adena -->
		<production id="17416" count="1" /> <!-- Helios Shaper -->
	</item>
	<item>
		<ingredient id="17425" count="1" /> <!-- Helios Caster -->
		<ingredient id="57" count="110596875" /> <!-- Adena -->
		<production id="17416" count="1" /> <!-- Helios Shaper -->
	</item>
	<item>
		<ingredient id="17426" count="1" /> <!-- Helios Retributer -->
		<ingredient id="57" count="110596875" /> <!-- Adena -->
		<production id="17416" count="1" /> <!-- Helios Shaper -->
	</item>
	<item>
		<ingredient id="17427" count="1" /> <!-- Helios Dual Swords -->
		<ingredient id="57" count="110596875" /> <!-- Adena -->
		<production id="17416" count="1" /> <!-- Helios Shaper -->
	</item>
	<item>
		<ingredient id="17428" count="1" /> <!-- Helios Dual Daggers -->
		<ingredient id="57" count="110596875" /> <!-- Adena -->
		<production id="17416" count="1" /> <!-- Helios Shaper -->
	</item>
	<item>
		<ingredient id="17429" count="1" /> <!-- Helios Dual Blunt Weapons -->
		<ingredient id="57" count="110596875" /> <!-- Adena -->
		<production id="17416" count="1" /> <!-- Helios Shaper -->
	</item>
	<item>
		<ingredient id="17416" count="1" /> <!-- Helios Shaper -->
		<ingredient id="57" count="110596875" /> <!-- Adena -->
		<production id="17417" count="1" /> <!-- Helios Cutter -->
	</item>
	<item>
		<ingredient id="17418" count="1" /> <!-- Helios Slasher -->
		<ingredient id="57" count="110596875" /> <!-- Adena -->
		<production id="17417" count="1" /> <!-- Helios Cutter -->
	</item>
	<item>
		<ingredient id="17419" count="1" /> <!-- Helios Avenger -->
		<ingredient id="57" count="110596875" /> <!-- Adena -->
		<production id="17417" count="1" /> <!-- Helios Cutter -->
	</item>
	<item>
		<ingredient id="17420" count="1" /> <!-- Helios Fighter -->
		<ingredient id="57" count="110596875" /> <!-- Adena -->
		<production id="17417" count="1" /> <!-- Helios Cutter -->
	</item>
	<item>
		<ingredient id="17421" count="1" /> <!-- Helios Stormer -->
		<ingredient id="57" count="110596875" /> <!-- Adena -->
		<production id="17417" count="1" /> <!-- Helios Cutter -->
	</item>
	<item>
		<ingredient id="17422" count="1" /> <!-- Helios Thrower -->
		<ingredient id="57" count="110596875" /> <!-- Adena -->
		<production id="17417" count="1" /> <!-- Helios Cutter -->
	</item>
	<item>
		<ingredient id="17423" count="1" /> <!-- Helios Guardian -->
		<ingredient id="57" count="110596875" /> <!-- Adena -->
		<production id="17417" count="1" /> <!-- Helios Cutter -->
	</item>
	<item>
		<ingredient id="17424" count="1" /> <!-- Helios Buster -->
		<ingredient id="57" count="110596875" /> <!-- Adena -->
		<production id="17417" count="1" /> <!-- Helios Cutter -->
	</item>
	<item>
		<ingredient id="17425" count="1" /> <!-- Helios Caster -->
		<ingredient id="57" count="110596875" /> <!-- Adena -->
		<production id="17417" count="1" /> <!-- Helios Cutter -->
	</item>
	<item>
		<ingredient id="17426" count="1" /> <!-- Helios Retributer -->
		<ingredient id="57" count="110596875" /> <!-- Adena -->
		<production id="17417" count="1" /> <!-- Helios Cutter -->
	</item>
	<item>
		<ingredient id="17427" count="1" /> <!-- Helios Dual Swords -->
		<ingredient id="57" count="110596875" /> <!-- Adena -->
		<production id="17417" count="1" /> <!-- Helios Cutter -->
	</item>
	<item>
		<ingredient id="17428" count="1" /> <!-- Helios Dual Daggers -->
		<ingredient id="57" count="110596875" /> <!-- Adena -->
		<production id="17417" count="1" /> <!-- Helios Cutter -->
	</item>
	<item>
		<ingredient id="17429" count="1" /> <!-- Helios Dual Blunt Weapons -->
		<ingredient id="57" count="110596875" /> <!-- Adena -->
		<production id="17417" count="1" /> <!-- Helios Cutter -->
	</item>
	<item>
		<ingredient id="17416" count="1" /> <!-- Helios Shaper -->
		<ingredient id="57" count="110596875" /> <!-- Adena -->
		<production id="17418" count="1" /> <!-- Helios Slasher -->
	</item>
	<item>
		<ingredient id="17417" count="1" /> <!-- Helios Cutter -->
		<ingredient id="57" count="110596875" /> <!-- Adena -->
		<production id="17418" count="1" /> <!-- Helios Slasher -->
	</item>
	<item>
		<ingredient id="17419" count="1" /> <!-- Helios Avenger -->
		<ingredient id="57" count="110596875" /> <!-- Adena -->
		<production id="17418" count="1" /> <!-- Helios Slasher -->
	</item>
	<item>
		<ingredient id="17420" count="1" /> <!-- Helios Fighter -->
		<ingredient id="57" count="110596875" /> <!-- Adena -->
		<production id="17418" count="1" /> <!-- Helios Slasher -->
	</item>
	<item>
		<ingredient id="17421" count="1" /> <!-- Helios Stormer -->
		<ingredient id="57" count="110596875" /> <!-- Adena -->
		<production id="17418" count="1" /> <!-- Helios Slasher -->
	</item>
	<item>
		<ingredient id="17422" count="1" /> <!-- Helios Thrower -->
		<ingredient id="57" count="110596875" /> <!-- Adena -->
		<production id="17418" count="1" /> <!-- Helios Slasher -->
	</item>
	<item>
		<ingredient id="17423" count="1" /> <!-- Helios Guardian -->
		<ingredient id="57" count="110596875" /> <!-- Adena -->
		<production id="17418" count="1" /> <!-- Helios Slasher -->
	</item>
	<item>
		<ingredient id="17424" count="1" /> <!-- Helios Buster -->
		<ingredient id="57" count="110596875" /> <!-- Adena -->
		<production id="17418" count="1" /> <!-- Helios Slasher -->
	</item>
	<item>
		<ingredient id="17425" count="1" /> <!-- Helios Caster -->
		<ingredient id="57" count="110596875" /> <!-- Adena -->
		<production id="17418" count="1" /> <!-- Helios Slasher -->
	</item>
	<item>
		<ingredient id="17426" count="1" /> <!-- Helios Retributer -->
		<ingredient id="57" count="110596875" /> <!-- Adena -->
		<production id="17418" count="1" /> <!-- Helios Slasher -->
	</item>
	<item>
		<ingredient id="17427" count="1" /> <!-- Helios Dual Swords -->
		<ingredient id="57" count="110596875" /> <!-- Adena -->
		<production id="17418" count="1" /> <!-- Helios Slasher -->
	</item>
	<item>
		<ingredient id="17428" count="1" /> <!-- Helios Dual Daggers -->
		<ingredient id="57" count="110596875" /> <!-- Adena -->
		<production id="17418" count="1" /> <!-- Helios Slasher -->
	</item>
	<item>
		<ingredient id="17429" count="1" /> <!-- Helios Dual Blunt Weapons -->
		<ingredient id="57" count="110596875" /> <!-- Adena -->
		<production id="17418" count="1" /> <!-- Helios Slasher -->
	</item>
	<item>
		<ingredient id="17416" count="1" /> <!-- Helios Shaper -->
		<ingredient id="57" count="110596875" /> <!-- Adena -->
		<production id="17419" count="1" /> <!-- Helios Avenger -->
	</item>
	<item>
		<ingredient id="17417" count="1" /> <!-- Helios Cutter -->
		<ingredient id="57" count="110596875" /> <!-- Adena -->
		<production id="17419" count="1" /> <!-- Helios Avenger -->
	</item>
	<item>
		<ingredient id="17418" count="1" /> <!-- Helios Slasher -->
		<ingredient id="57" count="110596875" /> <!-- Adena -->
		<production id="17419" count="1" /> <!-- Helios Avenger -->
	</item>
	<item>
		<ingredient id="17420" count="1" /> <!-- Helios Fighter -->
		<ingredient id="57" count="110596875" /> <!-- Adena -->
		<production id="17419" count="1" /> <!-- Helios Avenger -->
	</item>
	<item>
		<ingredient id="17421" count="1" /> <!-- Helios Stormer -->
		<ingredient id="57" count="110596875" /> <!-- Adena -->
		<production id="17419" count="1" /> <!-- Helios Avenger -->
	</item>
	<item>
		<ingredient id="17422" count="1" /> <!-- Helios Thrower -->
		<ingredient id="57" count="110596875" /> <!-- Adena -->
		<production id="17419" count="1" /> <!-- Helios Avenger -->
	</item>
	<item>
		<ingredient id="17423" count="1" /> <!-- Helios Guardian -->
		<ingredient id="57" count="110596875" /> <!-- Adena -->
		<production id="17419" count="1" /> <!-- Helios Avenger -->
	</item>
	<item>
		<ingredient id="17424" count="1" /> <!-- Helios Buster -->
		<ingredient id="57" count="110596875" /> <!-- Adena -->
		<production id="17419" count="1" /> <!-- Helios Avenger -->
	</item>
	<item>
		<ingredient id="17425" count="1" /> <!-- Helios Caster -->
		<ingredient id="57" count="110596875" /> <!-- Adena -->
		<production id="17419" count="1" /> <!-- Helios Avenger -->
	</item>
	<item>
		<ingredient id="17426" count="1" /> <!-- Helios Retributer -->
		<ingredient id="57" count="110596875" /> <!-- Adena -->
		<production id="17419" count="1" /> <!-- Helios Avenger -->
	</item>
	<item>
		<ingredient id="17427" count="1" /> <!-- Helios Dual Swords -->
		<ingredient id="57" count="110596875" /> <!-- Adena -->
		<production id="17419" count="1" /> <!-- Helios Avenger -->
	</item>
	<item>
		<ingredient id="17428" count="1" /> <!-- Helios Dual Daggers -->
		<ingredient id="57" count="110596875" /> <!-- Adena -->
		<production id="17419" count="1" /> <!-- Helios Avenger -->
	</item>
	<item>
		<ingredient id="17429" count="1" /> <!-- Helios Dual Blunt Weapons -->
		<ingredient id="57" count="110596875" /> <!-- Adena -->
		<production id="17419" count="1" /> <!-- Helios Avenger -->
	</item>
	<item>
		<ingredient id="17416" count="1" /> <!-- Helios Shaper -->
		<ingredient id="57" count="110596875" /> <!-- Adena -->
		<production id="17420" count="1" /> <!-- Helios Fighter -->
	</item>
	<item>
		<ingredient id="17417" count="1" /> <!-- Helios Cutter -->
		<ingredient id="57" count="110596875" /> <!-- Adena -->
		<production id="17420" count="1" /> <!-- Helios Fighter -->
	</item>
	<item>
		<ingredient id="17418" count="1" /> <!-- Helios Slasher -->
		<ingredient id="57" count="110596875" /> <!-- Adena -->
		<production id="17420" count="1" /> <!-- Helios Fighter -->
	</item>
	<item>
		<ingredient id="17419" count="1" /> <!-- Helios Avenger -->
		<ingredient id="57" count="110596875" /> <!-- Adena -->
		<production id="17420" count="1" /> <!-- Helios Fighter -->
	</item>
	<item>
		<ingredient id="17421" count="1" /> <!-- Helios Stormer -->
		<ingredient id="57" count="110596875" /> <!-- Adena -->
		<production id="17420" count="1" /> <!-- Helios Fighter -->
	</item>
	<item>
		<ingredient id="17422" count="1" /> <!-- Helios Thrower -->
		<ingredient id="57" count="110596875" /> <!-- Adena -->
		<production id="17420" count="1" /> <!-- Helios Fighter -->
	</item>
	<item>
		<ingredient id="17423" count="1" /> <!-- Helios Guardian -->
		<ingredient id="57" count="110596875" /> <!-- Adena -->
		<production id="17420" count="1" /> <!-- Helios Fighter -->
	</item>
	<item>
		<ingredient id="17424" count="1" /> <!-- Helios Buster -->
		<ingredient id="57" count="110596875" /> <!-- Adena -->
		<production id="17420" count="1" /> <!-- Helios Fighter -->
	</item>
	<item>
		<ingredient id="17425" count="1" /> <!-- Helios Caster -->
		<ingredient id="57" count="110596875" /> <!-- Adena -->
		<production id="17420" count="1" /> <!-- Helios Fighter -->
	</item>
	<item>
		<ingredient id="17426" count="1" /> <!-- Helios Retributer -->
		<ingredient id="57" count="110596875" /> <!-- Adena -->
		<production id="17420" count="1" /> <!-- Helios Fighter -->
	</item>
	<item>
		<ingredient id="17427" count="1" /> <!-- Helios Dual Swords -->
		<ingredient id="57" count="110596875" /> <!-- Adena -->
		<production id="17420" count="1" /> <!-- Helios Fighter -->
	</item>
	<item>
		<ingredient id="17428" count="1" /> <!-- Helios Dual Daggers -->
		<ingredient id="57" count="110596875" /> <!-- Adena -->
		<production id="17420" count="1" /> <!-- Helios Fighter -->
	</item>
	<item>
		<ingredient id="17429" count="1" /> <!-- Helios Dual Blunt Weapons -->
		<ingredient id="57" count="110596875" /> <!-- Adena -->
		<production id="17420" count="1" /> <!-- Helios Fighter -->
	</item>
	<item>
		<ingredient id="17416" count="1" /> <!-- Helios Shaper -->
		<ingredient id="57" count="110596875" /> <!-- Adena -->
		<production id="17421" count="1" /> <!-- Helios Stormer -->
	</item>
	<item>
		<ingredient id="17417" count="1" /> <!-- Helios Cutter -->
		<ingredient id="57" count="110596875" /> <!-- Adena -->
		<production id="17421" count="1" /> <!-- Helios Stormer -->
	</item>
	<item>
		<ingredient id="17418" count="1" /> <!-- Helios Slasher -->
		<ingredient id="57" count="110596875" /> <!-- Adena -->
		<production id="17421" count="1" /> <!-- Helios Stormer -->
	</item>
	<item>
		<ingredient id="17419" count="1" /> <!-- Helios Avenger -->
		<ingredient id="57" count="110596875" /> <!-- Adena -->
		<production id="17421" count="1" /> <!-- Helios Stormer -->
	</item>
	<item>
		<ingredient id="17420" count="1" /> <!-- Helios Fighter -->
		<ingredient id="57" count="110596875" /> <!-- Adena -->
		<production id="17421" count="1" /> <!-- Helios Stormer -->
	</item>
	<item>
		<ingredient id="17422" count="1" /> <!-- Helios Thrower -->
		<ingredient id="57" count="110596875" /> <!-- Adena -->
		<production id="17421" count="1" /> <!-- Helios Stormer -->
	</item>
	<item>
		<ingredient id="17423" count="1" /> <!-- Helios Guardian -->
		<ingredient id="57" count="110596875" /> <!-- Adena -->
		<production id="17421" count="1" /> <!-- Helios Stormer -->
	</item>
	<item>
		<ingredient id="17424" count="1" /> <!-- Helios Buster -->
		<ingredient id="57" count="110596875" /> <!-- Adena -->
		<production id="17421" count="1" /> <!-- Helios Stormer -->
	</item>
	<item>
		<ingredient id="17425" count="1" /> <!-- Helios Caster -->
		<ingredient id="57" count="110596875" /> <!-- Adena -->
		<production id="17421" count="1" /> <!-- Helios Stormer -->
	</item>
	<item>
		<ingredient id="17426" count="1" /> <!-- Helios Retributer -->
		<ingredient id="57" count="110596875" /> <!-- Adena -->
		<production id="17421" count="1" /> <!-- Helios Stormer -->
	</item>
	<item>
		<ingredient id="17427" count="1" /> <!-- Helios Dual Swords -->
		<ingredient id="57" count="110596875" /> <!-- Adena -->
		<production id="17421" count="1" /> <!-- Helios Stormer -->
	</item>
	<item>
		<ingredient id="17428" count="1" /> <!-- Helios Dual Daggers -->
		<ingredient id="57" count="110596875" /> <!-- Adena -->
		<production id="17421" count="1" /> <!-- Helios Stormer -->
	</item>
	<item>
		<ingredient id="17429" count="1" /> <!-- Helios Dual Blunt Weapons -->
		<ingredient id="57" count="110596875" /> <!-- Adena -->
		<production id="17421" count="1" /> <!-- Helios Stormer -->
	</item>
	<item>
		<ingredient id="17416" count="1" /> <!-- Helios Shaper -->
		<ingredient id="57" count="110596875" /> <!-- Adena -->
		<production id="17422" count="1" /> <!-- Helios Thrower -->
	</item>
	<item>
		<ingredient id="17417" count="1" /> <!-- Helios Cutter -->
		<ingredient id="57" count="110596875" /> <!-- Adena -->
		<production id="17422" count="1" /> <!-- Helios Thrower -->
	</item>
	<item>
		<ingredient id="17418" count="1" /> <!-- Helios Slasher -->
		<ingredient id="57" count="110596875" /> <!-- Adena -->
		<production id="17422" count="1" /> <!-- Helios Thrower -->
	</item>
	<item>
		<ingredient id="17419" count="1" /> <!-- Helios Avenger -->
		<ingredient id="57" count="110596875" /> <!-- Adena -->
		<production id="17422" count="1" /> <!-- Helios Thrower -->
	</item>
	<item>
		<ingredient id="17420" count="1" /> <!-- Helios Fighter -->
		<ingredient id="57" count="110596875" /> <!-- Adena -->
		<production id="17422" count="1" /> <!-- Helios Thrower -->
	</item>
	<item>
		<ingredient id="17421" count="1" /> <!-- Helios Stormer -->
		<ingredient id="57" count="110596875" /> <!-- Adena -->
		<production id="17422" count="1" /> <!-- Helios Thrower -->
	</item>
	<item>
		<ingredient id="17423" count="1" /> <!-- Helios Guardian -->
		<ingredient id="57" count="110596875" /> <!-- Adena -->
		<production id="17422" count="1" /> <!-- Helios Thrower -->
	</item>
	<item>
		<ingredient id="17424" count="1" /> <!-- Helios Buster -->
		<ingredient id="57" count="110596875" /> <!-- Adena -->
		<production id="17422" count="1" /> <!-- Helios Thrower -->
	</item>
	<item>
		<ingredient id="17425" count="1" /> <!-- Helios Caster -->
		<ingredient id="57" count="110596875" /> <!-- Adena -->
		<production id="17422" count="1" /> <!-- Helios Thrower -->
	</item>
	<item>
		<ingredient id="17426" count="1" /> <!-- Helios Retributer -->
		<ingredient id="57" count="110596875" /> <!-- Adena -->
		<production id="17422" count="1" /> <!-- Helios Thrower -->
	</item>
	<item>
		<ingredient id="17427" count="1" /> <!-- Helios Dual Swords -->
		<ingredient id="57" count="110596875" /> <!-- Adena -->
		<production id="17422" count="1" /> <!-- Helios Thrower -->
	</item>
	<item>
		<ingredient id="17428" count="1" /> <!-- Helios Dual Daggers -->
		<ingredient id="57" count="110596875" /> <!-- Adena -->
		<production id="17422" count="1" /> <!-- Helios Thrower -->
	</item>
	<item>
		<ingredient id="17429" count="1" /> <!-- Helios Dual Blunt Weapons -->
		<ingredient id="57" count="110596875" /> <!-- Adena -->
		<production id="17422" count="1" /> <!-- Helios Thrower -->
	</item>
	<item>
		<ingredient id="17416" count="1" /> <!-- Helios Shaper -->
		<ingredient id="57" count="110596875" /> <!-- Adena -->
		<production id="17423" count="1" /> <!-- Helios Guardian -->
	</item>
	<item>
		<ingredient id="17417" count="1" /> <!-- Helios Cutter -->
		<ingredient id="57" count="110596875" /> <!-- Adena -->
		<production id="17423" count="1" /> <!-- Helios Guardian -->
	</item>
	<item>
		<ingredient id="17418" count="1" /> <!-- Helios Slasher -->
		<ingredient id="57" count="110596875" /> <!-- Adena -->
		<production id="17423" count="1" /> <!-- Helios Guardian -->
	</item>
	<item>
		<ingredient id="17419" count="1" /> <!-- Helios Avenger -->
		<ingredient id="57" count="110596875" /> <!-- Adena -->
		<production id="17423" count="1" /> <!-- Helios Guardian -->
	</item>
	<item>
		<ingredient id="17420" count="1" /> <!-- Helios Fighter -->
		<ingredient id="57" count="110596875" /> <!-- Adena -->
		<production id="17423" count="1" /> <!-- Helios Guardian -->
	</item>
	<item>
		<ingredient id="17421" count="1" /> <!-- Helios Stormer -->
		<ingredient id="57" count="110596875" /> <!-- Adena -->
		<production id="17423" count="1" /> <!-- Helios Guardian -->
	</item>
	<item>
		<ingredient id="17422" count="1" /> <!-- Helios Thrower -->
		<ingredient id="57" count="110596875" /> <!-- Adena -->
		<production id="17423" count="1" /> <!-- Helios Guardian -->
	</item>
	<item>
		<ingredient id="17424" count="1" /> <!-- Helios Buster -->
		<ingredient id="57" count="110596875" /> <!-- Adena -->
		<production id="17423" count="1" /> <!-- Helios Guardian -->
	</item>
	<item>
		<ingredient id="17425" count="1" /> <!-- Helios Caster -->
		<ingredient id="57" count="110596875" /> <!-- Adena -->
		<production id="17423" count="1" /> <!-- Helios Guardian -->
	</item>
	<item>
		<ingredient id="17426" count="1" /> <!-- Helios Retributer -->
		<ingredient id="57" count="110596875" /> <!-- Adena -->
		<production id="17423" count="1" /> <!-- Helios Guardian -->
	</item>
	<item>
		<ingredient id="17427" count="1" /> <!-- Helios Dual Swords -->
		<ingredient id="57" count="110596875" /> <!-- Adena -->
		<production id="17423" count="1" /> <!-- Helios Guardian -->
	</item>
	<item>
		<ingredient id="17428" count="1" /> <!-- Helios Dual Daggers -->
		<ingredient id="57" count="110596875" /> <!-- Adena -->
		<production id="17423" count="1" /> <!-- Helios Guardian -->
	</item>
	<item>
		<ingredient id="17429" count="1" /> <!-- Helios Dual Blunt Weapons -->
		<ingredient id="57" count="110596875" /> <!-- Adena -->
		<production id="17423" count="1" /> <!-- Helios Guardian -->
	</item>
	<item>
		<ingredient id="17416" count="1" /> <!-- Helios Shaper -->
		<ingredient id="57" count="110596875" /> <!-- Adena -->
		<production id="17424" count="1" /> <!-- Helios Buster -->
	</item>
	<item>
		<ingredient id="17417" count="1" /> <!-- Helios Cutter -->
		<ingredient id="57" count="110596875" /> <!-- Adena -->
		<production id="17424" count="1" /> <!-- Helios Buster -->
	</item>
	<item>
		<ingredient id="17418" count="1" /> <!-- Helios Slasher -->
		<ingredient id="57" count="110596875" /> <!-- Adena -->
		<production id="17424" count="1" /> <!-- Helios Buster -->
	</item>
	<item>
		<ingredient id="17419" count="1" /> <!-- Helios Avenger -->
		<ingredient id="57" count="110596875" /> <!-- Adena -->
		<production id="17424" count="1" /> <!-- Helios Buster -->
	</item>
	<item>
		<ingredient id="17420" count="1" /> <!-- Helios Fighter -->
		<ingredient id="57" count="110596875" /> <!-- Adena -->
		<production id="17424" count="1" /> <!-- Helios Buster -->
	</item>
	<item>
		<ingredient id="17421" count="1" /> <!-- Helios Stormer -->
		<ingredient id="57" count="110596875" /> <!-- Adena -->
		<production id="17424" count="1" /> <!-- Helios Buster -->
	</item>
	<item>
		<ingredient id="17422" count="1" /> <!-- Helios Thrower -->
		<ingredient id="57" count="110596875" /> <!-- Adena -->
		<production id="17424" count="1" /> <!-- Helios Buster -->
	</item>
	<item>
		<ingredient id="17423" count="1" /> <!-- Helios Guardian -->
		<ingredient id="57" count="110596875" /> <!-- Adena -->
		<production id="17424" count="1" /> <!-- Helios Buster -->
	</item>
	<item>
		<ingredient id="17425" count="1" /> <!-- Helios Caster -->
		<ingredient id="57" count="110596875" /> <!-- Adena -->
		<production id="17424" count="1" /> <!-- Helios Buster -->
	</item>
	<item>
		<ingredient id="17426" count="1" /> <!-- Helios Retributer -->
		<ingredient id="57" count="110596875" /> <!-- Adena -->
		<production id="17424" count="1" /> <!-- Helios Buster -->
	</item>
	<item>
		<ingredient id="17427" count="1" /> <!-- Helios Dual Swords -->
		<ingredient id="57" count="110596875" /> <!-- Adena -->
		<production id="17424" count="1" /> <!-- Helios Buster -->
	</item>
	<item>
		<ingredient id="17428" count="1" /> <!-- Helios Dual Daggers -->
		<ingredient id="57" count="110596875" /> <!-- Adena -->
		<production id="17424" count="1" /> <!-- Helios Buster -->
	</item>
	<item>
		<ingredient id="17429" count="1" /> <!-- Helios Dual Blunt Weapons -->
		<ingredient id="57" count="110596875" /> <!-- Adena -->
		<production id="17424" count="1" /> <!-- Helios Buster -->
	</item>
	<item>
		<ingredient id="17416" count="1" /> <!-- Helios Shaper -->
		<ingredient id="57" count="110596875" /> <!-- Adena -->
		<production id="17425" count="1" /> <!-- Helios Caster -->
	</item>
	<item>
		<ingredient id="17417" count="1" /> <!-- Helios Cutter -->
		<ingredient id="57" count="110596875" /> <!-- Adena -->
		<production id="17425" count="1" /> <!-- Helios Caster -->
	</item>
	<item>
		<ingredient id="17418" count="1" /> <!-- Helios Slasher -->
		<ingredient id="57" count="110596875" /> <!-- Adena -->
		<production id="17425" count="1" /> <!-- Helios Caster -->
	</item>
	<item>
		<ingredient id="17419" count="1" /> <!-- Helios Avenger -->
		<ingredient id="57" count="110596875" /> <!-- Adena -->
		<production id="17425" count="1" /> <!-- Helios Caster -->
	</item>
	<item>
		<ingredient id="17420" count="1" /> <!-- Helios Fighter -->
		<ingredient id="57" count="110596875" /> <!-- Adena -->
		<production id="17425" count="1" /> <!-- Helios Caster -->
	</item>
	<item>
		<ingredient id="17421" count="1" /> <!-- Helios Stormer -->
		<ingredient id="57" count="110596875" /> <!-- Adena -->
		<production id="17425" count="1" /> <!-- Helios Caster -->
	</item>
	<item>
		<ingredient id="17422" count="1" /> <!-- Helios Thrower -->
		<ingredient id="57" count="110596875" /> <!-- Adena -->
		<production id="17425" count="1" /> <!-- Helios Caster -->
	</item>
	<item>
		<ingredient id="17423" count="1" /> <!-- Helios Guardian -->
		<ingredient id="57" count="110596875" /> <!-- Adena -->
		<production id="17425" count="1" /> <!-- Helios Caster -->
	</item>
	<item>
		<ingredient id="17424" count="1" /> <!-- Helios Buster -->
		<ingredient id="57" count="110596875" /> <!-- Adena -->
		<production id="17425" count="1" /> <!-- Helios Caster -->
	</item>
	<item>
		<ingredient id="17426" count="1" /> <!-- Helios Retributer -->
		<ingredient id="57" count="110596875" /> <!-- Adena -->
		<production id="17425" count="1" /> <!-- Helios Caster -->
	</item>
	<item>
		<ingredient id="17427" count="1" /> <!-- Helios Dual Swords -->
		<ingredient id="57" count="110596875" /> <!-- Adena -->
		<production id="17425" count="1" /> <!-- Helios Caster -->
	</item>
	<item>
		<ingredient id="17428" count="1" /> <!-- Helios Dual Daggers -->
		<ingredient id="57" count="110596875" /> <!-- Adena -->
		<production id="17425" count="1" /> <!-- Helios Caster -->
	</item>
	<item>
		<ingredient id="17429" count="1" /> <!-- Helios Dual Blunt Weapons -->
		<ingredient id="57" count="110596875" /> <!-- Adena -->
		<production id="17425" count="1" /> <!-- Helios Caster -->
	</item>
	<item>
		<ingredient id="17416" count="1" /> <!-- Helios Shaper -->
		<ingredient id="57" count="110596875" /> <!-- Adena -->
		<production id="17426" count="1" /> <!-- Helios Retributer -->
	</item>
	<item>
		<ingredient id="17417" count="1" /> <!-- Helios Cutter -->
		<ingredient id="57" count="110596875" /> <!-- Adena -->
		<production id="17426" count="1" /> <!-- Helios Retributer -->
	</item>
	<item>
		<ingredient id="17418" count="1" /> <!-- Helios Slasher -->
		<ingredient id="57" count="110596875" /> <!-- Adena -->
		<production id="17426" count="1" /> <!-- Helios Retributer -->
	</item>
	<item>
		<ingredient id="17419" count="1" /> <!-- Helios Avenger -->
		<ingredient id="57" count="110596875" /> <!-- Adena -->
		<production id="17426" count="1" /> <!-- Helios Retributer -->
	</item>
	<item>
		<ingredient id="17420" count="1" /> <!-- Helios Fighter -->
		<ingredient id="57" count="110596875" /> <!-- Adena -->
		<production id="17426" count="1" /> <!-- Helios Retributer -->
	</item>
	<item>
		<ingredient id="17421" count="1" /> <!-- Helios Stormer -->
		<ingredient id="57" count="110596875" /> <!-- Adena -->
		<production id="17426" count="1" /> <!-- Helios Retributer -->
	</item>
	<item>
		<ingredient id="17422" count="1" /> <!-- Helios Thrower -->
		<ingredient id="57" count="110596875" /> <!-- Adena -->
		<production id="17426" count="1" /> <!-- Helios Retributer -->
	</item>
	<item>
		<ingredient id="17423" count="1" /> <!-- Helios Guardian -->
		<ingredient id="57" count="110596875" /> <!-- Adena -->
		<production id="17426" count="1" /> <!-- Helios Retributer -->
	</item>
	<item>
		<ingredient id="17424" count="1" /> <!-- Helios Buster -->
		<ingredient id="57" count="110596875" /> <!-- Adena -->
		<production id="17426" count="1" /> <!-- Helios Retributer -->
	</item>
	<item>
		<ingredient id="17425" count="1" /> <!-- Helios Caster -->
		<ingredient id="57" count="110596875" /> <!-- Adena -->
		<production id="17426" count="1" /> <!-- Helios Retributer -->
	</item>
	<item>
		<ingredient id="17427" count="1" /> <!-- Helios Dual Swords -->
		<ingredient id="57" count="110596875" /> <!-- Adena -->
		<production id="17426" count="1" /> <!-- Helios Retributer -->
	</item>
	<item>
		<ingredient id="17428" count="1" /> <!-- Helios Dual Daggers -->
		<ingredient id="57" count="110596875" /> <!-- Adena -->
		<production id="17426" count="1" /> <!-- Helios Retributer -->
	</item>
	<item>
		<ingredient id="17429" count="1" /> <!-- Helios Dual Blunt Weapons -->
		<ingredient id="57" count="110596875" /> <!-- Adena -->
		<production id="17426" count="1" /> <!-- Helios Retributer -->
	</item>
	<item>
		<ingredient id="17416" count="1" /> <!-- Helios Shaper -->
		<ingredient id="57" count="110596875" /> <!-- Adena -->
		<production id="17427" count="1" /> <!-- Helios Dual Swords -->
	</item>
	<item>
		<ingredient id="17417" count="1" /> <!-- Helios Cutter -->
		<ingredient id="57" count="110596875" /> <!-- Adena -->
		<production id="17427" count="1" /> <!-- Helios Dual Swords -->
	</item>
	<item>
		<ingredient id="17418" count="1" /> <!-- Helios Slasher -->
		<ingredient id="57" count="110596875" /> <!-- Adena -->
		<production id="17427" count="1" /> <!-- Helios Dual Swords -->
	</item>
	<item>
		<ingredient id="17419" count="1" /> <!-- Helios Avenger -->
		<ingredient id="57" count="110596875" /> <!-- Adena -->
		<production id="17427" count="1" /> <!-- Helios Dual Swords -->
	</item>
	<item>
		<ingredient id="17420" count="1" /> <!-- Helios Fighter -->
		<ingredient id="57" count="110596875" /> <!-- Adena -->
		<production id="17427" count="1" /> <!-- Helios Dual Swords -->
	</item>
	<item>
		<ingredient id="17421" count="1" /> <!-- Helios Stormer -->
		<ingredient id="57" count="110596875" /> <!-- Adena -->
		<production id="17427" count="1" /> <!-- Helios Dual Swords -->
	</item>
	<item>
		<ingredient id="17422" count="1" /> <!-- Helios Thrower -->
		<ingredient id="57" count="110596875" /> <!-- Adena -->
		<production id="17427" count="1" /> <!-- Helios Dual Swords -->
	</item>
	<item>
		<ingredient id="17423" count="1" /> <!-- Helios Guardian -->
		<ingredient id="57" count="110596875" /> <!-- Adena -->
		<production id="17427" count="1" /> <!-- Helios Dual Swords -->
	</item>
	<item>
		<ingredient id="17424" count="1" /> <!-- Helios Buster -->
		<ingredient id="57" count="110596875" /> <!-- Adena -->
		<production id="17427" count="1" /> <!-- Helios Dual Swords -->
	</item>
	<item>
		<ingredient id="17425" count="1" /> <!-- Helios Caster -->
		<ingredient id="57" count="110596875" /> <!-- Adena -->
		<production id="17427" count="1" /> <!-- Helios Dual Swords -->
	</item>
	<item>
		<ingredient id="17426" count="1" /> <!-- Helios Retributer -->
		<ingredient id="57" count="110596875" /> <!-- Adena -->
		<production id="17427" count="1" /> <!-- Helios Dual Swords -->
	</item>
	<item>
		<ingredient id="17428" count="1" /> <!-- Helios Dual Daggers -->
		<ingredient id="57" count="110596875" /> <!-- Adena -->
		<production id="17427" count="1" /> <!-- Helios Dual Swords -->
	</item>
	<item>
		<ingredient id="17429" count="1" /> <!-- Helios Dual Blunt Weapons -->
		<ingredient id="57" count="110596875" /> <!-- Adena -->
		<production id="17427" count="1" /> <!-- Helios Dual Swords -->
	</item>
	<item>
		<ingredient id="17416" count="1" /> <!-- Helios Shaper -->
		<ingredient id="57" count="110596875" /> <!-- Adena -->
		<production id="17428" count="1" /> <!-- Helios Dual Daggers -->
	</item>
	<item>
		<ingredient id="17417" count="1" /> <!-- Helios Cutter -->
		<ingredient id="57" count="110596875" /> <!-- Adena -->
		<production id="17428" count="1" /> <!-- Helios Dual Daggers -->
	</item>
	<item>
		<ingredient id="17418" count="1" /> <!-- Helios Slasher -->
		<ingredient id="57" count="110596875" /> <!-- Adena -->
		<production id="17428" count="1" /> <!-- Helios Dual Daggers -->
	</item>
	<item>
		<ingredient id="17419" count="1" /> <!-- Helios Avenger -->
		<ingredient id="57" count="110596875" /> <!-- Adena -->
		<production id="17428" count="1" /> <!-- Helios Dual Daggers -->
	</item>
	<item>
		<ingredient id="17420" count="1" /> <!-- Helios Fighter -->
		<ingredient id="57" count="110596875" /> <!-- Adena -->
		<production id="17428" count="1" /> <!-- Helios Dual Daggers -->
	</item>
	<item>
		<ingredient id="17421" count="1" /> <!-- Helios Stormer -->
		<ingredient id="57" count="110596875" /> <!-- Adena -->
		<production id="17428" count="1" /> <!-- Helios Dual Daggers -->
	</item>
	<item>
		<ingredient id="17422" count="1" /> <!-- Helios Thrower -->
		<ingredient id="57" count="110596875" /> <!-- Adena -->
		<production id="17428" count="1" /> <!-- Helios Dual Daggers -->
	</item>
	<item>
		<ingredient id="17423" count="1" /> <!-- Helios Guardian -->
		<ingredient id="57" count="110596875" /> <!-- Adena -->
		<production id="17428" count="1" /> <!-- Helios Dual Daggers -->
	</item>
	<item>
		<ingredient id="17424" count="1" /> <!-- Helios Buster -->
		<ingredient id="57" count="110596875" /> <!-- Adena -->
		<production id="17428" count="1" /> <!-- Helios Dual Daggers -->
	</item>
	<item>
		<ingredient id="17425" count="1" /> <!-- Helios Caster -->
		<ingredient id="57" count="110596875" /> <!-- Adena -->
		<production id="17428" count="1" /> <!-- Helios Dual Daggers -->
	</item>
	<item>
		<ingredient id="17426" count="1" /> <!-- Helios Retributer -->
		<ingredient id="57" count="110596875" /> <!-- Adena -->
		<production id="17428" count="1" /> <!-- Helios Dual Daggers -->
	</item>
	<item>
		<ingredient id="17427" count="1" /> <!-- Helios Dual Swords -->
		<ingredient id="57" count="110596875" /> <!-- Adena -->
		<production id="17428" count="1" /> <!-- Helios Dual Daggers -->
	</item>
	<item>
		<ingredient id="17429" count="1" /> <!-- Helios Dual Blunt Weapons -->
		<ingredient id="57" count="110596875" /> <!-- Adena -->
		<production id="17428" count="1" /> <!-- Helios Dual Daggers -->
	</item>
	<item>
		<ingredient id="17416" count="1" /> <!-- Helios Shaper -->
		<ingredient id="57" count="110596875" /> <!-- Adena -->
		<production id="17429" count="1" /> <!-- Helios Dual Blunt Weapons -->
	</item>
	<item>
		<ingredient id="17417" count="1" /> <!-- Helios Cutter -->
		<ingredient id="57" count="110596875" /> <!-- Adena -->
		<production id="17429" count="1" /> <!-- Helios Dual Blunt Weapons -->
	</item>
	<item>
		<ingredient id="17418" count="1" /> <!-- Helios Slasher -->
		<ingredient id="57" count="110596875" /> <!-- Adena -->
		<production id="17429" count="1" /> <!-- Helios Dual Blunt Weapons -->
	</item>
	<item>
		<ingredient id="17419" count="1" /> <!-- Helios Avenger -->
		<ingredient id="57" count="110596875" /> <!-- Adena -->
		<production id="17429" count="1" /> <!-- Helios Dual Blunt Weapons -->
	</item>
	<item>
		<ingredient id="17420" count="1" /> <!-- Helios Fighter -->
		<ingredient id="57" count="110596875" /> <!-- Adena -->
		<production id="17429" count="1" /> <!-- Helios Dual Blunt Weapons -->
	</item>
	<item>
		<ingredient id="17421" count="1" /> <!-- Helios Stormer -->
		<ingredient id="57" count="110596875" /> <!-- Adena -->
		<production id="17429" count="1" /> <!-- Helios Dual Blunt Weapons -->
	</item>
	<item>
		<ingredient id="17422" count="1" /> <!-- Helios Thrower -->
		<ingredient id="57" count="110596875" /> <!-- Adena -->
		<production id="17429" count="1" /> <!-- Helios Dual Blunt Weapons -->
	</item>
	<item>
		<ingredient id="17423" count="1" /> <!-- Helios Guardian -->
		<ingredient id="57" count="110596875" /> <!-- Adena -->
		<production id="17429" count="1" /> <!-- Helios Dual Blunt Weapons -->
	</item>
	<item>
		<ingredient id="17424" count="1" /> <!-- Helios Buster -->
		<ingredient id="57" count="110596875" /> <!-- Adena -->
		<production id="17429" count="1" /> <!-- Helios Dual Blunt Weapons -->
	</item>
	<item>
		<ingredient id="17425" count="1" /> <!-- Helios Caster -->
		<ingredient id="57" count="110596875" /> <!-- Adena -->
		<production id="17429" count="1" /> <!-- Helios Dual Blunt Weapons -->
	</item>
	<item>
		<ingredient id="17426" count="1" /> <!-- Helios Retributer -->
		<ingredient id="57" count="110596875" /> <!-- Adena -->
		<production id="17429" count="1" /> <!-- Helios Dual Blunt Weapons -->
	</item>
	<item>
		<ingredient id="17427" count="1" /> <!-- Helios Dual Swords -->
		<ingredient id="57" count="110596875" /> <!-- Adena -->
		<production id="17429" count="1" /> <!-- Helios Dual Blunt Weapons -->
	</item>
	<item>
		<ingredient id="17428" count="1" /> <!-- Helios Dual Daggers -->
		<ingredient id="57" count="110596875" /> <!-- Adena -->
		<production id="17429" count="1" /> <!-- Helios Dual Blunt Weapons -->
	</item>
</list>